Workbook

Sheet READ ME
A1: kim23-lab-index HPメタデータ（labratory_ktech記事）
A3: note.com「Kim23 Test Laboratory」全293記事のメタデータです。
A4: 本サイトの content/articles/*.md フロントマター（src/content.config.ts のスキーマ）に対応する形式で整理しています。
A6: ① 記事メタデータ
A7: title / car / ecu / purpose / note_url / related / date は content.config.ts のフィールド名と一致。
A8: slug列は content/articles/{slug}.md として保存する際のファイル名（拡張子なし）候補です。
A9: related列は関連記事のslugをカンマ区切りで格納（同一車種内のSTEP前後関係を自動リンク）。
A10: このシートの1行がそのまま1記事のフロントマターの元データになります。
A12: ② 車種展開_Pivot用
A13: 1記事が複数車種に該当する場合は行を複製し、1行=1記事×1車種に正規化。
A14: Excelで選択→挿入→ピボットテーブル、で車種・カテゴリ・ECU等を自由に集計・分析できます。
A16: ③ 車種×カテゴリ集計
... A26: データ取得日: 2026-09-12 / 出典: https://note.com/labratory_ktech

Sheet 記事メタデータ
A1: slug | B1: title | C1: car | D1: ecu | E1: purpose | F1: note_url | G1: related | H1: date | I1: category | J1: step | K1: magazines | L1: tags | M1: price
A2: misc-84a7b3 | B2: 初めましてなのか、お久しぶりなのか？ | C2: （共通・車種特定なし） | E2: 初めましての方は初めまして！ お久しぶり？の方はお久しぶりです。 | F2: https://note.com/labratory_ktech/n/nf4258784a7b3 | H2: 2025-02-18 | I2: その他 | K2: （未分類） | L2: #情報 #データ #ノウハウ #伝承 #ECU #ECUチューニング | M2: 0
A3: misc-linkecu-e865c2 | B3: 自動車 フルコン化に必要なモノ | C3: （共通・車種特定なし） | D3: LINKECU | E3: まず、この記事をベースにこの後のフルコン化の記事を読んで貰いたい対象者を設定しますね(´・ω・｀) 対象者 ・自分の車を LINKECU、M… | F3: https://note.com/labratory_ktech/n/n192a1be865c2 | H3: 2025-02-20 | I3: 基礎知識・準備 | K3: ECUフルコン化への道 | L3: #フルコン #ECU #LINKECU #ECUチューニング #安定化電源 | M3: 0
A4: misc-228e07 | B4: 安定化電源を使う理由 | C4: （共通・車種特定なし） | E4: 電気系のテストをするのに安定化電源が必要だと言ったのですが、その観点を説明します。 | F4: https://note.com/labratory_ktech/n/nfe3377228e07 | H4: 2025-02-23 | I4: 基礎知識・準備 | K4: ECUフルコン化への道 | L4: #テスト #バッテリー #電源 #電圧 #安定化電源 | M4: 0
A5: misc-linkecu-6aecda | B5: フルコン勉強にお勧めのECUは？ | C5: （共通・車種特定なし） | D5: LINKECU/MaxxECU/MOTEC/EMTRON/Haltech | E5: ECUフルコン化をやってみようー！ と、思ったときにどのECUを選ぶか悩むと思います。 | F5: https://note.com/labratory_ktech/n/n9881036aecda | H5: 2025-02-24 | I5: 基礎知識・準備 | K5: ECUフルコン化への道 | L5: #機能 #セッティング #フルコン #ECU #LINKECU #ecuセッティング #MaxxECU #MoTeC #Haltech #EMTRON | M5: 0
A6: misc-linkecu-160fa8 | B6: 燃料セッティング 空燃比計とは？ | C6: （共通・車種特定なし） | D6: LINKECU | E6: 始めにECUフルコンのセッティングやるのに空燃比計センサー付けないといけないんでしょ？って思っている人！ 空燃比計買う前に、ちょっと待ってく… | F6: https://note.com/labratory_ktech/n/n182b31160fa8 | H6: 2025-02-26 | I6: 基礎知識・準備 | K6: ECUフルコン化への道 | L6: #アナログ #CAN #フルコン #ECU #LINKECU #空燃比計 | M6: 0
A7: misc-linkecu-711682 | B7: 初心者？がECUフルコンを選定するのに一番大事なこと | C7: （共通・車種特定なし） | D7: LINKECU/MaxxECU | E7: 以前にお勧めのECUがLINKECUとMaxxECUだと推奨しました。 | F7: https://note.com/labratory_ktech/n/n612e8f711682 | H7: 2025-02-27 | I7: 基礎知識・準備 | K7: ECUフルコン化への道 | L7: #設定 #信号 #フルコン #LINKECU #MaxxECU #TRIGGER設定 | M7: 0
A8: misc-linkecu-275a47 | B8: LINKECU MAXXECU どの機種選べばいいの？ | C8: （共通・車種特定なし） | D8: LINKECU/MaxxECU | E8: フルコンこれから始める人にはLINKECUか MAXXECUをお勧めしていました。 | F8: https://note.com/labratory_ktech/n/n5515d1275a47 | H8: 2025-03-01 | I8: 他社ECU・機器情報 | K8: LINKECU 関連/MaxxECU フルコン化への道/ECUフルコン化への道 | L8: #フルコン #LINKECU #車いじり #ECUチューニング #MaxxECU | M8: 0
A9: esse-cc2978 | B9: フルコン化の第１の壁 吸気圧力センサ特性どうやって測定するの？ | C9: エッセ(ESSE) | E9: フルコン化が一般的にされている車両の場合は、吸気圧力センサの特性がソフトウェアのプルダウンで選べるのですが、プルダウンで選べない場合、センサ… | F9: https://note.com/labratory_ktech/n/n4fe44ccc2978 | H9: 2025-03-02 | I9: センサ・計測データ | K9: エッセ ESSE LINKECU フルコン化 への道/ECUフルコン化への道/吸気圧力センサ 電圧-圧力特性測定結果 | L9: #データ #圧力 #センサ #MAPセンサ #吸気圧力センサ #PressureSensor | M9: 0
A10: fd3s-linkecu-774f15 | B10: LINKECU PLUG IN FD3S 後期 電源供給 | C10: FD3S(RX-7) | D10: LINKECU | E10: FD3Sプラグインに対して電源供給する方法を紹介します UNBOXカバースライドさせます 開けると基盤が入ってます 袋から出してUSBケーブ… | F10: https://note.com/labratory_ktech/n/n4a4ba4774f15 | H10: 2025-03-03 | I10: 基礎知識・準備 | K10: LINKECU 関連/ECUフルコン化への道/FD3S LINKECU フルコン化への道 | L10: #セッティング #ECU #LINKECU #フルコン化 #PCLINK #電圧供給 #FD3S後期 | M10: 0
A11: ae86-linkecu-460ba3 | B11: AE86 4AG 吸気圧力センサ特性 品番89421-12020 | C11: AE86 | D11: LINKECU/MaxxECU | E11: 以下注意事項測定データは、あるセンサにおいて、n=1～5のデータによるもの、測定誤差、サンプル誤差などを含んだものです。 | F11: https://note.com/labratory_ktech/n/n3b3112460ba3 | H11: 2025-03-03 | I11: センサ・計測データ | K11: 吸気圧力センサ 電圧-圧力特性測定結果 | L11: #AE86 #実験結果 #LINKECU #測定結果 #MaxxECU #圧力センサ #MAPセンサ #吸気圧力センサ #4AG | M11: 2000
A12: misc-linkecu-16c728 | B12: LINKECU 通電 と アンロック作業 | C12: （共通・車種特定なし） | D12: LINKECU | E12: LINKECUを動かすにはアンロック作業なるものが必要になります。 | F12: https://note.com/labratory_ktech/n/n4a2c4616c728 | H12: 2025-03-03 | I12: 基礎知識・準備 | K12: ECUフルコン化への道 | L12: #ソフトウェア #ECU #アンロック #LINKECU #フルコン化 #安定化電源 | M12: 0
A13: misc-8b7628 | B13: AE92 4AG 吸気圧力センサ特性 品番 80420-20300 | C13: （共通・車種特定なし） | E13: 以下注意事項 測定データは、あるセンサにおいて、n=1～5のデータによるもの、測定誤差、サンプル誤差などを含んだものです。 | F13: https://note.com/labratory_ktech/n/nee83a58b7628 | H13: 2025-03-04 | I13: センサ・計測データ | K13: 吸気圧力センサ 電圧-圧力特性測定結果 | L13: #データ #校正 #測定結果 #圧力センサ #AE92 #吸気圧力センサ #電圧圧力 | M13: 2000
A14: misc-2b1b60 | B14: フルコン化への道 ビギーバック配線とは？ | C14: （共通・車種特定なし） | E14: ビギーバックとは？Piggyback（ピギーバック）とは、もともと「背負う」「おんぶする」という意味の英語です。 | F14: https://note.com/labratory_ktech/n/n4a159e2b1b60 | H14: 2025-03-05 | I14: 基礎知識・準備 | K14: ECUフルコン化への道 | L14: #配線 #フルコン #ECU #ECUチューニング #ビギーバック | M14: 0
A15: altoworks-step0-4670ac | B15: HA22Sフルコン化 STEP0 ECUピンアサイン | C15: アルトワークス(HA22S/HA23S) | E15: 純正ECUをフルコン化する際に、まずはじめに純正のピンアサインを把握する必要があります。 | F15: https://note.com/labratory_ktech/n/na152494670ac | G15: altoworks-linkecu-step1-362693 | H15: 2025-03-08 | I15: STEP本編（フルコン化手順） | J15: STEP0 | K15: 新規格 K6A フルコン化情報/アルトワークス フルコン化 HA22S事例 | L15: #ダウンロード #純正 #フルコン #Step0 #ECUピンアサイン #HA22Sフルコン化 | M15: 500
A16: altoworks-linkecu-step1-362693 | B16: HA22S K6A フルコン化 STEP1 ビギーバックハーネス | C16: アルトワークス(HA22S/HA23S) | D16: LINKECU | E16: ビギーバックハーネスとは？ビギーバックハーネスは何か？使用をお勧めする理由を、以下の記事で記載しています。 | F16: https://note.com/labratory_ktech/n/ne2f733362693 | G16: altoworks-linkecu-step2-e48ff8, altoworks-step0-4670ac | H16: 2025-03-08 | I16: STEP本編（フルコン化手順） | J16: STEP1 | K16: アルトワークス フルコン化 HA22S事例 | L16: #配線 #LINKECU #フルコン化 #アルトワークス #HA22S #K6A #ビギーバックハーネス #ECU延長ハーネス | M16: 0
A17: altoworks-linkecu-f776fe | B17: HA22S K6A アルトワークスフルコン化 | C17: アルトワークス(HA22S/HA23S) | D17: LINKECU | E17: ECUフルコン化の内容を紹介しようとしていましたが、ベースとなる車両やエンジンを何にしようとかと悩んでいました。 | F17: https://note.com/labratory_ktech/n/n3eb953f776fe | H17: 2025-03-08 | I17: 基礎知識・準備（車種別） | K17: アルトワークス フルコン化 HA22S事例 | L17: #フルコン #LINKECU #ECUチューニング #アルトワークス #HA22S #K6A | M17: 0
A18: cappuccino-linkecu-e16ea7 | B18: F6A アルトカプチーノ 吸気圧力センサ特性 品番 18590-64D00 | C18: カプチーノ(F6A) | D18: LINKECU | E18: 以下注意事項 測定データは、あるセンサにおいて、n=1～5のデータによるもの、測定誤差、サンプル誤差などを含んだものです。 | F18: https://note.com/labratory_ktech/n/neaa561e16ea7 | H18: 2025-03-08 | I18: センサ・計測データ | K18: 吸気圧力センサ 電圧-圧力特性測定結果 | L18: #データ #センサー #実験結果 #LINKECU #ECUチューニング #F6A #圧力センサ特性 | M18: 3000
A19: misc-2668a9 | B19: インジェクター燃料圧力制御の基礎 燃料のリターン、リターンレスシステムとは？ | C19: （共通・車種特定なし） | E19: エンジンの出力UPを行う、ECUセッティングをするのに燃料圧力の制御方法の理解が必要だと思います。 | F19: https://note.com/labratory_ktech/n/n0f32362668a9 | H19: 2025-03-08 | I19: センサ・計測データ | K19: 燃料、インジェクター関連 無効噴射時間 | L19: #燃料 #ECUチューニング #ecuセッティング #インジェクター #燃圧 #吸気圧力 #燃料噴射量 | M19: 0
A20: altoworks-linkecu-step2-e48ff8 | B20: HA22S LINKECU フルコン化 STEP2 電源供給 | C20: アルトワークス(HA22S/HA23S) | D20: LINKECU | E20: HA22Sの車両とECU間にビギーバックハーネスがある前提で進めます。 | F20: https://note.com/labratory_ktech/n/n3bb503e48ff8 | G20: altoworks-linkecu-step1-362693, altoworks-linkecu-step3-ff1549 | H20: 2025-03-09 | I20: STEP本編（フルコン化手順） | J20: STEP2 | K20: アルトワークス フルコン化 HA22S事例/ECUフルコン化への道 | L20: #電源 #配線 #LINKECU #フルコン化 #HA22S #K6A #ビギーバック | M20: 0
A21: altoworks-b01abe | B21: 温度センサ校正の基礎知識 分圧とは？ | C21: アルトワークス(HA22S/HA23S) | E21: エンジンの水温センサ吸気温度センサ等のサーミスタを用いた抵抗変化による温度計測をするのに、分圧の知識は絶対に必要になります。 | F21: https://note.com/labratory_ktech/n/ne58f6db01abe | H21: 2025-03-10 | I21: 基礎知識・準備 | K21: アルトワークス フルコン化 HA22S事例/ECUフルコン化への道 | L21: #抵抗 #電圧 #オームの法則 #温度センサ #分圧 #センサ校正 | M21: 0
A22: altoworks-linkecu-step3-ff1549 | B22: HA22S フルコン化 STEP3 スロットル信号入力とアナログ入力エラー設定の観点 | C22: アルトワークス(HA22S/HA23S) | D22: LINKECU | E22: おさらいSTEP2では電源が入るところまで確認しました。 | F22: https://note.com/labratory_ktech/n/n58a1cbff1549 | G22: altoworks-linkecu-step2-e48ff8, altoworks-linkecu-step4-ceb9fa | H22: 2025-03-11 | I22: STEP本編（フルコン化手順） | J22: STEP3 | K22: アルトワークス フルコン化 HA22S事例/ECUフルコン化への道 | L22: #設定 #配線 #LINKECU #ECUチューニング #フルコン化 #スロットル #開度信号 | M22: 100
A23: altoworks-075bb5 | B23: HA22 温度センサー 温度-抵抗特性測定結果 | C23: アルトワークス(HA22S/HA23S) | E23: 温度センサの特性を測定する方法を紹介しました。 | F23: https://note.com/labratory_ktech/n/n6cea0c075bb5 | H23: 2025-03-13 | I23: 部品選定・レビュー | K23: アルトワークス フルコン化 HA22S事例/HA22S 部品関連情報/温度センサ関連 | M23: 500
A24: misc-a2b1f2 | B24: 温度センサの温度-抵抗特性 と B定数 | C24: （共通・車種特定なし） | E24: 自動車用に使われている温度センサとは？自動車のエンジン制御で使われる、水温センサや吸気温度センサは、サーミスタ (Thermistor)TYPEがほとんどです。 | F24: https://note.com/labratory_ktech/n/nf904daa2b1f2 | H24: 2025-03-13 | I24: センサ・計測データ | K24: LINKECU 関連/温度センサ関連/ECUフルコン化への道 | L24: #温度 #センサ #ECUチューニング #抵抗値 #温度センサー #水温センサー #吸気温度センサー #B定数 | M24: 0
A25: copen-linkecu-6815ae | B25: JB-DET コペン 吸気圧力センサ 品番 89421-97201 特性測定結果 | C25: コペン(L880K) | D25: LINKECU | E25: 以下注意事項 測定データは、あるセンサにおいて、n=1のデータによるもの、測定誤差、サンプル誤差などを含んだものです。 | F25: https://note.com/labratory_ktech/n/nd325a66815ae | H25: 2025-03-14 | I25: センサ・計測データ | K25: 吸気圧力センサ 電圧-圧力特性測定結果/コペン L880K フルコン化 | L25: #コペン #l880k #LINKECU #ECUチューニング #フルコン化 #圧力センサ #吸気圧力センサ #圧力センサ特性 | M25: 2000
A26: altoworks-linkecu-91bebe | B26: HA22S 吸気圧力センサ HITACHI製 品番 18590-78G50 特性測定結果 | C26: アルトワークス(HA22S/HA23S) | D26: LINKECU | E26: 以下注意事項 測定データは、あるセンサにおいて、n=1～5程度のデータによるもの、測定誤差、サンプル誤差などを含んだものです。 | F26: https://note.com/labratory_ktech/n/n6cfee691bebe | H26: 2025-03-15 | I26: センサ・計測データ | K26: アルトワークス フルコン化 HA22S事例/吸気圧力センサ 電圧-圧力特性測定結果 | L26: #フルコン #LINKECU #ECUチューニング #フルコン化 #アルトワークス #K6A #圧力センサー #MAPセンサ #確認結果 | M26: 2000
A27: altoworks-linkecu-step4-ceb9fa | B27: HA22S フルコン化 STEP4 吸気圧力信号入力 と センサCaliblation設定の観点 | C27: アルトワークス(HA22S/HA23S) | D27: LINKECU | E27: おさらいSTEP3ではスロットルポジションセンサの動作を確認しました。 | F27: https://note.com/labratory_ktech/n/nb5f07fceb9fa | G27: altoworks-linkecu-step3-ff1549, altoworks-linkecu-step5-e41aba | H27: 2025-03-16 | I27: STEP本編（フルコン化手順） | J27: STEP4 | K27: アルトワークス フルコン化 HA22S事例/ECUフルコン化への道 | L27: #LINKECU #フルコン化 #HA22S #K6A #LINKECUセッティング #圧力センサ #MAPセンサ #吸気圧力センサ | M27: 0
A28: altoworks-linkecu-b980ee | B28: HA23 吸気圧力センサ Denso製 品番 18590-79F00 特性測定結果 | C28: アルトワークス(HA22S/HA23S) | D28: LINKECU | E28: HA23等は、スロットルボディが流用されている、別の車種のエンジンが使用されている場合があります。 | F28: https://note.com/labratory_ktech/n/n0c63cbb980ee | H28: 2025-03-16 | I28: その他 | K28: （未分類） | L28: #データ #アルト #センサ #実験結果 #LINKECU #ECUチューニング #K6A #MAPセンサ #吸気圧力センサ #HA23 | M28: 2000
A29: misc-26b3d3 | B29: 燃料圧力と噴射量の関係性 | C29: （共通・車種特定なし） | E29: 燃料圧力と噴射量の関係は、ベルヌーイの定理と流体力学の基本原理を使って説明できます。 | F29: https://note.com/labratory_ktech/n/n57277926b3d3 | H29: 2025-03-17 | I29: センサ・計測データ | K29: 燃料、インジェクター関連 無効噴射時間/ECUフルコン化への道 | L29: #燃料 #平方根 #インジェクター #燃圧 #燃料圧力 #燃料圧力レギュレーター #噴射量 | M29: 0
A30: misc-bb3fb4 | B30: インジェクタ流量と馬力の関係 | C30: （共通・車種特定なし） | E30: 過去に自分が6気筒エンジンで1000ｃｃ/minインジェクターのDutyが85％だから、800馬力くらい出たかなー？ 等とつぶやくことがあっ… | F30: https://note.com/labratory_ktech/n/n5809cebb3fb4 | H30: 2025-03-18 | I30: センサ・計測データ | K30: 燃料、インジェクター関連 無効噴射時間/ECUフルコン化への道 | L30: #hp #馬力 #フルコン化 #ecuセッティング #Duty #インジェクター #馬力計算 #インジェクター噴射量 | M30: 200
A31: misc-linkecu-922d25 | B31: TA-HE21S ラパンSS 純正ECUピンアサイン エクセルファイル | C31: （共通・車種特定なし） | D31: LINKECU | E31: HA22S後期アルトワークスを事例にフルコン化作業を紹介しています。 | F31: https://note.com/labratory_ktech/n/n959df6922d25 | H31: 2025-03-19 | I31: 配線・ピンアサイン資料 | K31: 新規格 K6A フルコン化情報 | L31: #ダウンロード #整備書 #ラパン #フルコン化 #K6A #LINKECUセッティング #HE21S #ラパンSS #新規格K6A #純正ECU #ECUピンアサイン #TAHE21S | M31: 5000
A32: misc-6a1297 | B32: HN12等 F6A ターボ 吸気圧力センサ Denso製 品番 18590-76G50 特性測定結果 | C32: （共通・車種特定なし） | E32: スズキの車両は、スロットルボディが流用されている、別の車種のエンジンが使用されている場合があります。 | F32: https://note.com/labratory_ktech/n/n3cf1366a1297 | H32: 2025-03-21 | I32: センサ・計測データ | K32: 吸気圧力センサ 電圧-圧力特性測定結果 | L32: #データ #Kei #センサ #実験結果 #フルコン化 #ecuセッティング #フルコンセッティング #MAPセンサ #吸気圧力センサ #F6A #電圧圧力特性 #圧力センサ校正 | M32: 2000
A33: misc-motec-4c23e9 | B33: GM MAP SENSOR | C33: （共通・車種特定なし） | D33: MOTEC | E33: ECUフルコン化に必要な情報がすべて手に入る場所を作りたいと思い、Noteを書いています。 | F33: https://note.com/labratory_ktech/n/n966de44c23e9 | H33: 2025-03-21 | I33: センサ・計測データ | K33: 吸気圧力センサ 電圧-圧力特性測定結果 | L33: #Gm #センサ #フルコン化 #ecuセッティング #MoTeC #MAPセンサ #電圧圧力特性 #MAPSENSOR #GM1BAR #GM2BAR #GM3BAR | M33: 0
A34: misc-linkecu-733713 | B34: 温度センサ校正の基礎 LINKECU例 プルアップ抵抗 有り編 | C34: （共通・車種特定なし） | D34: LINKECU | E34: ふりかえり先ずは以下の記事を見て分圧の内容を理解しておいてください。 | F34: https://note.com/labratory_ktech/n/n8e1736733713 | H34: 2025-03-23 | I34: センサ・計測データ | K34: LINKECU 関連/温度センサ関連 | L34: #温度 #抵抗 #LINKECU #フルコン化 #ecuセッティング #プルアップ #LINKECUセッティング #温度センサ校正 #温度校正 | M34: 0
A35: misc-linkecu-451883 | B35: 温度センサ校正の基礎 LINKECU例 プルアップ抵抗OFF ビギーバック編 | C35: （共通・車種特定なし） | D35: LINKECU | E35: ふりかえりプルアップ抵抗有り時の、温度校正設定の概要を説明しました。 | F35: https://note.com/labratory_ktech/n/n0085d3451883 | H35: 2025-03-25 | I35: センサ・計測データ | K35: LINKECU 関連/温度センサ関連/ECUフルコン化への道 | L35: #抵抗 #LINKECU #フルコン化 #ecuセッティング #プルアップ #ビギーバック #温度センサ #プルアップ抵抗 #温度センサ校正 #ビギーバック配線 | M35: 500
A36: misc-linkecu-1d2d43 | B36: SARD1000cc/min 低抵抗 インジェクター | C36: （共通・車種特定なし） | D36: LINKECU | F36: https://note.com/labratory_ktech/n/nfb525f1d2d43 | H36: 2025-03-27 | I36: 部品選定・レビュー | K36: 車関係部品 写真置き場 | L36: #燃料 #LINKECU #フルコン化 #ecuセッティング #インジェクター | M36: 0
A37: misc-linkecu-660efd | B37: 1JZ 2JZ 等 ターボ用 吸気圧力センサ Denso製 品番 89421-12111 特性測定結果 | C37: （共通・車種特定なし） | D37: LINKECU | E37: エンジンに対して純正とは違う吸気圧力センサが取り付けられている可能性があります。 | F37: https://note.com/labratory_ktech/n/n9b53de660efd | H37: 2025-03-29 | I37: センサ・計測データ | K37: 吸気圧力センサ 電圧-圧力特性測定結果 | L37: #データ #センサ #実験結果 #LINKECU #LINKECUセッティング #1jz #圧力センサ #2JZ #MAPセンサ #圧力センサ校正 | M37: 2000
A38: altoworks-linkecu-step5-e41aba | B38: HA22S フルコン化 STEP5 温度センサ校正設定 | C38: アルトワークス(HA22S/HA23S) | D38: LINKECU | E38: おさらいSTEP4ではスロットルポジションセンサの動作を確認しました。 | F38: https://note.com/labratory_ktech/n/ne1c5b4e41aba | G38: altoworks-linkecu-step4-ceb9fa, altoworks-step5-2-865d7b | H38: 2025-03-29 | I38: STEP本編（フルコン化手順） | J38: STEP5 | K38: 新規格 K6A フルコン化情報/アルトワークス フルコン化 HA22S事例/温度センサ関連 | L38: #温度 #センサ #LINKECU #フルコン化 #アルトワークス #HA22S #K6A #LINKECUセッティング #新規格K6A #温度センサ校正 #センサ校正 | M38: 2000
A39: misc-emanage-191520 | B39: TRUST e-manage オプション 吸気圧力センサ 特性測定結果 | C39: （共通・車種特定なし） | D39: E-manage | E39: フルコンを使用した場合は、センサの特性が分かれば、ほとんどのセンサーが流用使用できます。 | F39: https://note.com/labratory_ktech/n/ndaf171191520 | H39: 2025-03-30 | I39: センサ・計測データ | K39: 吸気圧力センサ 電圧-圧力特性測定結果 | M39: 1000
A40: misc-linkecu-575188 | B40: MC21S K6A ワゴンR 純正ECUピンアサイン エクセルファイル | C40: （共通・車種特定なし） | D40: LINKECU | E40: HA22S後期アルトワークスを事例にフルコン化作業を紹介しています。 | F40: https://note.com/labratory_ktech/n/n522bbf575188 | H40: 2025-03-30 | I40: 配線・ピンアサイン資料 | K40: 新規格 K6A フルコン化情報 | L40: #ダウンロード #配線 #LINKECU #ECUチューニング #フルコン化 #K6A #LINKECUセッティング #新規格K6A #MC21S | M40: 2000
A41: altoworks-linkecu-step6-888601 | B41: HA22S フルコン化 STEP6 回転数トリガ設定 | C41: アルトワークス(HA22S/HA23S) | D41: LINKECU | E41: おさらいSTEP5では温度センサの入力と校正をしました。 | F41: https://note.com/labratory_ktech/n/nb50b3a888601 | G41: altoworks-linkecu-step5-3-0b2924, altoworks-linkecu-step7-3a2b38 | H41: 2025-03-30 | I41: STEP本編（フルコン化手順） | J41: STEP6 | K41: アルトワークス フルコン化 HA22S事例/ECUフルコン化への道 | L41: #配線 #Trigger #LINKECU #K6A #フルコンセッティング #LINKECUセッティング #新規格K6A #回転数信号 | M41: 100
A42: altoworks-linkecu-step7-3a2b38 | B42: HA22S フルコン化 STEP7 エンジン設定 | C42: アルトワークス(HA22S/HA23S) | D42: LINKECU | E42: おさらいSTEP6ではTrigger設定をして、エンジン回転数を認識させました。 | F42: https://note.com/labratory_ktech/n/n051d663a2b38 | G42: altoworks-linkecu-step6-888601, altoworks-linkecu-step8-a28e89 | H42: 2025-04-02 | I42: STEP本編（フルコン化手順） | J42: STEP7 | K42: 新規格 K6A フルコン化情報/アルトワークス フルコン化 HA22S事例 | L42: #エンジン #アルト #ECU #LINKECU #HA22S #K6A #フルコンセッティング #LINKECUセッティング #新規格K6A | M42: 0
A43: misc-linkecu-b13f31 | B43: ラパンSS 他 水温アラーム制御方法 | C43: （共通・車種特定なし） | D43: LINKECU | E43: タイトル画像の 右上 SUZUKIの車両についている水温のアラームですが、 純正ECUから信号を送って制御しているので、フルコン化して純正E… | F43: https://note.com/labratory_ktech/n/n146db3b13f31 | H43: 2025-04-07 | I43: センサ・計測データ | K43: 新規格 K6A フルコン化情報/温度センサ関連 | L43: #状態 #信号 #メーター #水温 #LINKECU #フルコン化 #ecuセッティング #Duty #LINKECUセッティング | M43: 3000
A44: porsche996-e0ad62 | B44: Porche 996 Turbo Bosch T-MAP Sensor 0 261 230 042 特性測定結果 | C44: Porsche996 | E44: Porche 996 の吸気圧力センサ特性を測る機会があったので、情報を置いておきます。 | F44: https://note.com/labratory_ktech/n/nc98c88e0ad62 | H44: 2025-04-08 | I44: センサ・計測データ | K44: 吸気圧力センサ 電圧-圧力特性測定結果/Porche 996フルコン化への道！ | L44: #データ #ポルシェ #センサ #Bosch #フルコン化 #ecuセッティング #フルコンセッティング #実験データ #圧力センサ #吸気圧力センサ #MAPSENSOR #Porche996 #MaxxEU | M44: 10000
A45: misc-linkecu-499cb9 | B45: エンジン回転数と周波数 周期サイクルタイムの関係性 | C45: （共通・車種特定なし） | D45: LINKECU/MaxxECU | E45: エンジンの回転数（RPM: Revolutions Per Minute）と周波数（Hz）、周期T（ｓ）の関係について説明します。 | F45: https://note.com/labratory_ktech/n/n16bbf9499cb9 | H45: 2025-04-09 | I45: センサ・計測データ | K45: 燃料、インジェクター関連 無効噴射時間/ECUフルコン化への道 | L45: #周波数 #計算 #エンジン #基礎知識 #回転数 #点火 #LINKECU #ecuセッティング #MaxxECU #点火時期 #点火タイミング #回転周期 #エンジンサイクル #点火Dwelltime #点火周期 | M45: 200
A46: misc-linkecu-9b257b | B46: 計測器 8CH オシロスコープ HANTECH 1008C | C46: （共通・車種特定なし） | D46: LINKECU/MaxxECU | E46: データ計測分析にはまずは、計測が必要です。 | F46: https://note.com/labratory_ktech/n/n9eda7c9b257b | H46: 2025-04-11 | I46: センサ・計測データ | K46: 計測器情報/ECUフルコン化への道 | L46: #信号 #計測 #センサ #フルコン #LINKECU #オシロスコープ #オシロ #ecuセッティング #MaxxECU #電圧波形 | M46: 0
A47: cappuccino-linkecu-step0-929164 | B47: カプチーノフルコン化 STEP0 EA11 F6A 純正ECUピンアサイン エクセルファイル | C47: カプチーノ(F6A) | D47: LINKECU/MaxxECU | E47: HA22S後期アルトワークスを事例にフルコン化作業を紹介しています。 | F47: https://note.com/labratory_ktech/n/n383740929164 | H47: 2025-04-12 | I47: STEP本編（フルコン化手順） | J47: STEP0 | K47: F6A カプチーノフルコン化への道 | L47: #ダウンロード #配線 #カプチーノ #ECU #LINKECU #フルコン化 #ecuセッティング #MaxxECU #K6A #フルコンセッティング #F6A #EA11 | M47: 2000
A48: misc-83caf9 | B48: 点火イグニッションコイルとイグナイターの有無について | C48: （共通・車種特定なし） | E48: ECUをフルコン化する際に、Ignition 点火に関する設定が必要です。 | F48: https://note.com/labratory_ktech/n/nf6f30283caf9 | H48: 2025-04-13 | I48: 基礎知識・準備 | K48: ECUフルコン化への道 | L48: #プラグ #コイル #フルコン #点火 #ECU #イグナイター #フルコン化 #イグニッション #点火コイル #Dwelltime | M48: 0
A49: misc-linkecu-1999b2 | B49: 卓上点火テスト板 製作 | C49: （共通・車種特定なし） | D49: LINKECU | E49: ふりかえり点火コイルの配線について概要を説明しました。 | F49: https://note.com/labratory_ktech/n/n3ed4371999b2 | H49: 2025-04-14 | I49: 基礎知識・準備 | K49: ECUフルコン化への道 | L49: #テスト #コイル #ECU #イグナイター #LINKECU #フルコンセッティング #点火時期 #点火コイル #タイミングライト #IGNITON | M49: 0
A50: altoworks-linkecu-step8-a28e89 | B50: HA22S フルコン化 STEP8 点火テスト | C50: アルトワークス(HA22S/HA23S) | D50: LINKECU | E50: エンジンの回転TRIGGERの設定をしました。 | F50: https://note.com/labratory_ktech/n/n2c4e23a28e89 | G50: altoworks-linkecu-step7-3a2b38, altoworks-linkecu-step9-6e88d5 | H50: 2025-04-22 | I50: STEP本編（フルコン化手順） | J50: STEP8 | K50: アルトワークス フルコン化 HA22S事例 | L50: #配線 #コイル #フルコン #点火 #LINKECU #ecuセッティング #点火信号 #点火基準 #点火テスト #Trigger基準 | M50: 0
A51: misc-linkecu-5d19f6 | B51: イグニッション・ドエルタイム（Dwell Time）とは？ | C51: （共通・車種特定なし） | D51: LINKECU | E51: ふりかえり点火コイルにパルス信号を入れるとプラグから火花が発生します。 | F51: https://note.com/labratory_ktech/n/n3d98615d19f6 | H51: 2025-04-24 | I51: センサ・計測データ | K51: ECUフルコン化への道/点火コイル Dwell timeまとめ | L51: #コイル #点火 #LINKECU #フルコンセッティング #サイクルタイム #エンジン回転数 #点火コイル #Dwelltime #点火時間 #点火ドウェルタイム | M51: 500
A52: misc-linkecu-9d34ab | B52: 市販メータを使った 圧力センサ校正をする際の注意点 | C52: （共通・車種特定なし） | D52: LINKECU | E52: 以前にフルコンやECUに設定する圧力センサの圧力－電圧特性を測定する方法を紹介しました。 | F52: https://note.com/labratory_ktech/n/na067499d34ab | H52: 2025-04-29 | I52: センサ・計測データ | K52: ECUフルコン化への道/吸気圧力センサ 電圧-圧力特性測定結果 | L52: #DeFi #表示 #校正 #圧力 #センサ #フルコン化 #ecuセッティング #フルコンセッティング #LINKECUセッティング #圧力センサ #ブースト計 #圧力電圧校正 | M52: 500
A53: misc-7bd62b | B53: ※注意：バッテリーカットターミナル付けたままスポーツ走行しないで！！！ | C53: （共通・車種特定なし） | E53: ECU設定した後、サーキット走行中に急にエンジン切れたんですけど・・・・ とか言われたので、問題の個所を色々調査をしましたー エンジンが切れ… | F53: https://note.com/labratory_ktech/n/n5ff81c7bd62b | H53: 2025-05-01 | I53: 部品選定・レビュー | K53: パーツレビュー | L53: #問題 #不具合 #配線 #エンジンストール #バッテリーカットターミナル #カットターミナル | M53: 0
A54: altoworks-linkecu-step9-6e88d5 | B54: HA22S フルコン化 STEP9 点火基準合わせ | C54: アルトワークス(HA22S/HA23S) | D54: LINKECU | E54: 振り返りLINKECUから点火コイルにIGNの配線をして、コイルから火花が飛ばせる様になりました。 | F54: https://note.com/labratory_ktech/n/n0042b76e88d5 | G54: altoworks-linkecu-step10-8958ff, altoworks-linkecu-step8-a28e89 | H54: 2025-05-03 | I54: STEP本編（フルコン化手順） | J54: STEP9 | K54: アルトワークス フルコン化 HA22S事例/ECUフルコン化への道 | L54: #エンジン #点火 #LINKECU #フルコン化 #ecuセッティング #フルコンセッティング #LINKECUセッティング #タイミングライト #点火基準合わせ | M54: 500
A55: cappuccino-4c7d9b | B55: カプチーノ F6A エアコン制御基板 ピンアサイン | C55: カプチーノ(F6A) | E55: カプチーノの純正ECUのピンアサインを紹介しました。 | F55: https://note.com/labratory_ktech/n/n4fd2474c7d9b | H55: 2025-05-08 | I55: 配線・ピンアサイン資料 | K55: F6A カプチーノフルコン化への道 | L55: #エアコン #制御 #カプチーノ #純正 #フルコン #フルコン化 #フルコンセッティング #エアコン制御 #F6A | M55: 1000
A56: misc-99eb44 | B56: ガスコイル コイルベンチマーク測定結果 | C56: （共通・車種特定なし） | E56: 注意事項測定データは、あるコイルのあるロットにおいて、測定誤差、サンプルバラツキ、製造誤差などを含んだものです。 | F56: https://note.com/labratory_ktech/n/nacb87d99eb44 | H56: 2025-05-13 | I56: センサ・計測データ | K56: 点火コイル Dwell timeまとめ | L56: #データ #サンプル #コイル #中華製 #ecuセッティング #測定結果 #フルコンセッティング #Dwelltime #コイルベンチマーク #測定データ #点火時間 #限界Dwelltime #ガスコイル | M56: 2000
A57: misc-linkecu-759452 | B57: 点火コイルの Dwell time 測定用 コイルベンチマーク | C57: （共通・車種特定なし） | D57: LINKECU | E57: イグニッション限界 Dwell timeをコイルベンチマークで測れることを紹介しました。 | F57: https://note.com/labratory_ktech/n/nab4ec5759452 | H57: 2025-05-13 | I57: センサ・計測データ | K57: ECUフルコン化への道/点火コイル Dwell timeまとめ | L57: #限界 #測定 #コイル #LINKECU #ecuセッティング #フルコンセッティング #点火コイル #Dwelltime #コイルベンチマーク | M57: 1000
A58: misc-81c254 | B58: EJ207 GC8 同時点火コイル コイルベンチマーク測定結果 | C58: （共通・車種特定なし） | E58: 注意事項測定データは、あるコイルのあるロットにおいて、測定誤差、サンプルバラツキ、製造誤差などを含んだものです。 | F58: https://note.com/labratory_ktech/n/ne0308281c254 | H58: 2025-05-14 | I58: センサ・計測データ | K58: 点火コイル Dwell timeまとめ | L58: #データ #インプレッサ #コイル #ecuセッティング #フルコンセッティング #GC8 #点火コイル #Dwelltime #EJ207 #コイルベンチマーク #限界Dwelltime #同時点火 | M58: 2000
A59: altoworks-linkecu-step10-8958ff | B59: HA22S LINKECU フルコン化 STEP10 車速入力 | C59: アルトワークス(HA22S/HA23S) | D59: LINKECU | E59: ふりかえり点火基準の設定やアナログ信号の入力が終わったので、次はデジタルインプットの設定をしていきます。 | F59: https://note.com/labratory_ktech/n/na48afe8958ff | G59: altoworks-linkecu-step10-2-38153c, altoworks-linkecu-step9-6e88d5 | H59: 2025-05-21 | I59: STEP本編（フルコン化手順） | J59: STEP10 | K59: 新規格 K6A フルコン化情報/アルトワークス フルコン化 HA22S事例 | L59: #確認 #設定 #LINKECU #フルコンセッティング #デジタルインプット #車速 #デジタル信号 #車速信号 #SPEED入力 #SPEEDINPUT | M59: 100
A60: misc-linkecu-step1-c991d6 | B60: CAN通信への道 STEP1 CAN信号送受信 | C60: （共通・車種特定なし） | D60: LINKECU/MaxxECU | E60: ECUやフルコンセッティングの情報を出していますが、後々CAN設定の知識を基にした事例を紹介しようとしていこうと考えています。 | F60: https://note.com/labratory_ktech/n/n632aa0c991d6 | G60: misc-linkecu-step1-fd6e1b | H60: 2025-05-22 | I60: STEP本編（フルコン化手順） | J60: STEP1 | K60: CAN 設定への道/ECUフルコン化への道 | L60: #設定 #信号 #CAN #機器 #canbus #LINKECU #MaxxECU #フルコンセッティング | M60: 0
A61: altoworks-linkecu-step11-7d733e | B61: HA22S LINKECU フルコン化 STEP11 ギヤ認識 | C61: アルトワークス(HA22S/HA23S) | D61: LINKECU | E61: ふりかえりSTEP10で車速信号が入力されました。 | F61: https://note.com/labratory_ktech/n/n072b717d733e | G61: altoworks-linkecu-step10-2-38153c, altoworks-linkecu-step12-1cdbb0 | H61: 2025-05-23 | I61: STEP本編（フルコン化手順） | J61: STEP11 | K61: アルトワークス フルコン化 HA22S事例/ECUフルコン化への道 | L61: #speed #回転数 #ecuセッティング #フルコンセッティング #LINKECUセッティング #車速 #ギヤ認識 #タイヤ外径 #GearDetection | M61: 200
A62: misc-linkecu-13b0e6 | B62: ECUMaster USB to CAN 使用手順と注意点 | C62: （共通・車種特定なし） | D62: LINKECU/ECUMaster(PMU/ADU/EMU) | E62: ECU master のUSB to CANが、CAN信号の観測にお勧めだと紹介しています。 | F62: https://note.com/labratory_ktech/n/n6668d413b0e6 | H62: 2025-05-23 | I62: CAN通信・周辺機器連携 | K62: CAN 設定への道/ECUフルコン化への道/ECUmaster PMU ADU関連 | L62: #PdM #CAN #canbus #LINKECU #ECUmaster #keypad #CAN設定 #CANセッティング #CANセットアップ #DASHモニタ | M62: 200
A63: misc-linkecu-2cbddc | B63: ECUmaster ADU アナログ入力 ギヤ設定 | C63: （共通・車種特定なし） | D63: LINKECU/ECUMaster(PMU/ADU/EMU) | E63: LINKECU で エンジン回転数と車速からギヤを認識する方法を紹介しました。 | F63: https://note.com/labratory_ktech/n/n5aa5f82cbddc | H63: 2025-05-27 | I63: CAN通信・周辺機器連携 | K63: ECUmaster PMU ADU関連 | L63: #設定 #アナログ #canbus #LINKECU #ecuセッティング #フルコンセッティング #ECUmaster #ADU #DASHDISPLAY #ギヤポジション #Aanloginput | M63: 1000
A64: altoworks-linkecu-6e5875 | B64: スイッチ入力の基礎 Hisideインプット Losideインプット プルアップ抵抗 プルダウン抵抗 | C64: アルトワークス(HA22S/HA23S) | D64: LINKECU | E64: ECUやフルコンの制御だけでなく、電子工作等にも活用できるスイッチ入力の基礎的な考え方を紹介します。 | F64: https://note.com/labratory_ktech/n/nc8a5ba6e5875 | H64: 2025-06-01 | I64: 基礎知識・準備 | K64: アルトワークス フルコン化 HA22S事例/ECUフルコン化への道 | L64: #スイッチ #入力 #フルコン #DI #LINKECU #プルダウン #プルアップ #フルコンセッティング #デジタルインプット #Pullup #スイッチ入力 | M64: 500
A65: fd3s-linkecu-110900 | B65: RX-7 FD3S 吸気圧力センサ特性 品番N3A1-18-211 100798-2131 | C65: FD3S(RX-7) | D65: LINKECU | E65: 以下注意事項 測定データは、あるセンサにおいて、n=1程度のデータによるもの、測定誤差、サンプル誤差などを含んだものです。 | F65: https://note.com/labratory_ktech/n/n9f7f14110900 | H65: 2025-06-03 | I65: センサ・計測データ | K65: 吸気圧力センサ 電圧-圧力特性測定結果 | L65: #データ #センサー #RX7 #FD3S #FD #LINKECU #フルコン化 #ecuセッティング #フルコンセッティング #実験データ #圧力センサ #電圧圧力特性 | M65: 2000
A66: altoworks-linkecu-step12-1cdbb0 | B66: HA22S LINKECU フルコン化 STEP12 デジタルインプット 電気負荷信号入力 | C66: アルトワークス(HA22S/HA23S) | D66: LINKECU | E66: 振り返り前回は車速信号を STEP10で入力させて、ギヤ認識をさせました。 | F66: https://note.com/labratory_ktech/n/n7c61e01cdbb0 | G66: altoworks-linkecu-step11-7d733e, altoworks-linkecu-step13-0eae4c | H66: 2025-06-04 | I66: STEP本編（フルコン化手順） | J66: STEP12 | K66: アルトワークス フルコン化 HA22S事例 | L66: #設定 #DI #LINKECU #フルコン化 #ecuセッティング #HA22S #K6A #LINKECUセッティング #デジタルインプット #電気負荷信号 #電気負荷 | M66: 100
A67: misc-linkecu-6e0042 | B67: MaxxECU フルコン化への道 始まるよ！ | C67: （共通・車種特定なし） | D67: LINKECU/MaxxECU | E67: LINKECUとMaxxECUが自分のお勧めです。 | F67: https://note.com/labratory_ktech/n/n5531386e0042 | H67: 2025-06-05 | I67: 他社ECU・機器情報 | K67: MaxxECU フルコン化への道 | L67: #DIY #配線 #フルコン #LINKECU #ecuセッティング #MaxxECU #フルコンセッティング #MaxxECUフルコン化 #Pinout | M67: 200
A68: roadster-maxxecu-eb9512 | B68: NB1 フルコン化への道 ECUピンアサイン | C68: ロードスター(NB8/NB1) | D68: MaxxECU | E68: 何はともあれフルコン化を進めるのに、プラグインECUじゃない場合は、ECUのピンアサイン情報が必要になります。 | F68: https://note.com/labratory_ktech/n/n53461beb9512 | H68: 2025-06-07 | I68: 配線・ピンアサイン資料 | K68: NB8 NB1ロードスター MaxxECU フルコン化への道 | L68: #ロードスター #NB #フルコン化 #ecuセッティング #MaxxECU #NBロードスター #NB1 #NB8 #MaxxECUフルコン化 | M68: 1000
A69: altoworks-linkecu-step13-0eae4c | B69: HA22S LINKECU フルコン化 STEP13 デジタルインプット ブロアファン信号入力 | C69: アルトワークス(HA22S/HA23S) | D69: LINKECU | E69: 振り返り前回STEP12では電気負荷を入力して、アイドルアップの準備ができました。 | F69: https://note.com/labratory_ktech/n/n21ee0a0eae4c | G69: altoworks-linkecu-step12-1cdbb0, altoworks-linkecu-step14-4613b9 | H69: 2025-06-07 | I69: STEP本編（フルコン化手順） | J69: STEP13 | K69: アルトワークス フルコン化 HA22S事例 | L69: #Link #セッティング #DI #LINKECU #ecuセッティング #フルコンセッティング #LINKECUセッティング #デジタルインプット #ブロアファン #スイッチ入力 #電気負荷信号 #Digitalinput | M69: 100
A70: roadster-maxxecu-773dd4 | B70: MaxxECUフルコン化 まず始めの作業 電源供給 と ソフトウェアダウンロード | C70: ロードスター(NB8/NB1) | D70: MaxxECU | E70: MaxxECUフルコンの設定をしていくのに、とにかく初めに電源を入れるところからが始めます。 | F70: https://note.com/labratory_ktech/n/ne89913773dd4 | H70: 2025-06-08 | I70: 他社ECU・機器情報 | K70: MaxxECU フルコン化への道/NB8 NB1ロードスター MaxxECU フルコン化への道 | L70: #通信 #電源 #ecuセッティング #MaxxECU #フルコンセッティング #安定化電源 #電源供給 #ピンアサイン #MaxxECUセッティング | M70: 100
A71: altoworks-linkecu-step14-4613b9 | B71: HA22S LINKECU フルコン化 STEP14 デジタルインプット エアコンリクエスト信号入力 | C71: アルトワークス(HA22S/HA23S) | D71: LINKECU | E71: 振り返り前回STEP13ではブロアーファン信号を入力して、アイドルアップの準備ができました。 | F71: https://note.com/labratory_ktech/n/n23416a4613b9 | G71: altoworks-linkecu-step13-0eae4c, altoworks-linkecu-step14-2-551b76 | H71: 2025-06-09 | I71: STEP本編（フルコン化手順） | J71: STEP14 | K71: アルトワークス フルコン化 HA22S事例 | L71: #エアコン #Link #DI #LINKECU #ecuセッティング #フルコンセッティング #デジタルインプット #エアコンリクエスト #LINKECU制御 | M71: 100
A72: altoworks-linkecu-step15-7877b4 | B72: HA22S LINKECU フルコン化 STEP15 デジタルインプット イグニッションKeyON 信号入力 ECU Holdパワーの準備 | C72: アルトワークス(HA22S/HA23S) | D72: LINKECU | E72: 振り返り前回STEP14ではエアコンリクエストのスイッチの入力してエアコン制御の準備が進みました。 | F72: https://note.com/labratory_ktech/n/nda6c7b7877b4 | G72: altoworks-linkecu-step14-4-c56164, altoworks-linkecu-step16-afcadf | H72: 2025-06-10 | I72: STEP本編（フルコン化手順） | J72: STEP15 | K72: 新規格 K6A フルコン化情報/アルトワークス フルコン化 HA22S事例/ECUフルコン化への道 | L72: #信号 #LINKECU #フルコン化 #ecuセッティング #HA22S #フルコンセッティング #イグニッション #デジタルインプット #LINKセッティング #イグニッションスイッチ #ECUホールドパワー #ステッピングモータアイドル制御 | M72: 100
A73: altoworks-linkecu-step16-afcadf | B73: HA22S LINKECU フルコン化 STEP16 デジタルインプット ブレーキスイッチ 信号入力 | C73: アルトワークス(HA22S/HA23S) | D73: LINKECU | E73: 振り返り前回STEP15ではイグニッションKey ONの信号を入力しECU HOLDパワー制御の準備が進みました。 | F73: https://note.com/labratory_ktech/n/n117100afcadf | G73: altoworks-linkecu-step15-7877b4, altoworks-linkecu-step17-c86c82 | H73: 2025-06-11 | I73: STEP本編（フルコン化手順） | J73: STEP16 | K73: 新規格 K6A フルコン化情報/アルトワークス フルコン化 HA22S事例 | L73: #入力 #ブレーキ #信号 #DI #LINKECU #ecuセッティング #フルコンセッティング #デジタルインプット #LINKセッティング #ブレーキスイッチ #ECU設定 | M73: 100
A74: altoworks-linkecu-step17-c86c82 | B74: HA22S LINKECU フルコン化 STEP17 アナログ入力 O2センサー Lambda 信号入力 | C74: アルトワークス(HA22S/HA23S) | D74: LINKECU | E74: 振り返り前回STEP16ではブレーキスイッチ信号を入力しクルーズコントロールや、アイドルアップ制御の準備が進みました。 | F74: https://note.com/labratory_ktech/n/n36e113c86c82 | G74: altoworks-linkecu-step16-afcadf, altoworks-linkecu-step18-468088 | H74: 2025-06-13 | I74: STEP本編（フルコン化手順） | J74: STEP17 | K74: 新規格 K6A フルコン化情報/アルトワークス フルコン化 HA22S事例 | L74: #lambda #LINKECU #フルコン化 #ecuセッティング #HA22S #LINKECUセッティング #O2センサー #アナログ入力 #信号入力 #Step17 | M74: 100
A75: altoworks-linkecu-step19-f71505 | B75: HA22S LINKECU フルコン化 STEP19 Aux出力 燃料ポンプリレー制御 | C75: アルトワークス(HA22S/HA23S) | D75: LINKECU | E75: 振り返り前回STEP18ではピギーバック制御でLINKECUが信号を見ているだけでしたが、タコメータ制御をLINKECUで乗っ取りました(｀… | F75: https://note.com/labratory_ktech/n/n94ab9bf71505 | G75: altoworks-linkecu-step18-468088, altoworks-linkecu-step20-1-b728df | H75: 2025-06-14 | I75: STEP本編（フルコン化手順） | J75: STEP19 | K75: アルトワークス フルコン化 HA22S事例/LINKECU 関連 | L75: #LINKECU #フルコン化 #HA22S #燃料ポンプ #フルコンセッティング #LINKECUセッティング #ビギーバック #Aux出力 #燃料ポンプリレー制御 | M75: 100
A76: altoworks-linkecu-step18-468088 | B76: HA22S LINKECU フルコン化 STEP18 Aux出力 タコメータ制御 | C76: アルトワークス(HA22S/HA23S) | D76: LINKECU | E76: 振り返り前回STEP17ではO2センサ信号を入力し、純正ECUの空燃比制御で14.7付近になっているかどうか把握ができるようになりました。 | F76: https://note.com/labratory_ktech/n/nbe600c468088 | G76: altoworks-linkecu-step17-c86c82, altoworks-linkecu-step19-f71505 | H76: 2025-06-14 | I76: STEP本編（フルコン化手順） | J76: STEP18 | K76: アルトワークス フルコン化 HA22S事例/LINKECU 関連 | L76: #信号 #LINKECU #フルコン化 #HA22S #フルコンセッティング #LINKECUセッティング #Step18 #Aux出力 #タコメータ制御 #タコメータ | M76: 100
A77: fd3s-linkecu-786b87 | B77: FD3S FC3S アペックス パワーFC ECU内温度センサ入力のプルアップ抵抗っていくつやねん！ | C77: FD3S(RX-7) | D77: LINKECU/Apexi PowerFC | E77: パワーFCをベースに他のフルコンECUをビギーバック動作させることを目的とします。 | F77: https://note.com/labratory_ktech/n/ne6a076786b87 | H77: 2025-06-14 | I77: 基礎知識・準備（車種別） | K77: FD3S LINKECU フルコン化への道 | L77: #FD3S #LINKECU #ecuセッティング #FC3S #プルアップ #LINKECUセッティング #アペックス #ビギーバック #温度センサ #パワーFC #温度入力 #プルアップ抵抗値 | M77: 500
A78: roadster-maxxecu-step2-4b2212 | B78: NB1 ロドスタ ロードスター MaxxECU Race フルコン化 STEP2 スロットルポジションセンサ 信号入力 アナログインプット | C78: ロードスター(NB8/NB1) | D78: MaxxECU | E78: 振り返りまずは電源入力出来たら次のステップへ行きましょう 今回はスロットルポジションセンサ信号の入力をしていきます。 | F78: https://note.com/labratory_ktech/n/n00d2384b2212 | G78: roadster-linkecu-step3-35987a, roadster-maxxecu-step1-be4007 | H78: 2025-06-14 | I78: STEP本編（フルコン化手順） | J78: STEP2 | K78: MaxxECU フルコン化への道/NB8 NB1ロードスター MaxxECU フルコン化への道 | L78: #Race #フルコン化 #スロットル #MaxxECU #NB1 #ロドスタ #NB8 #MaxxECUフルコン化 #スロットルポジションセンサ信号入力 #スロットルポジション | M78: 100
A79: roadster-maxxecu-step1-be4007 | B79: NB1 ロドスタ MaxxECU Race フルコン化 STEP1 電源配線 | C79: ロードスター(NB8/NB1) | D79: MaxxECU | E79: MaxxECU ピンアサイン MaxxECU のピンアサインは以下に置いておきます。 | F79: https://note.com/labratory_ktech/n/nd4c40cbe4007 | G79: roadster-maxxecu-step2-4b2212 | H79: 2025-06-14 | I79: STEP本編（フルコン化手順） | J79: STEP1 | K79: NB8 NB1ロードスター MaxxECU フルコン化への道 | L79: #ロードスター #Step1 #フルコン化 #ecuセッティング #MaxxECU #NB1 #ロドスタ #電源配線 #N8 #MaxxECUセッティング | M79: 0
A80: altoworks-linkecu-step20-2-60c771 | B80: HA22S LINKECU フルコン化 STEP20-2ワイドバンド空燃比入力 Intenal Lambda制御編（Fury） | C80: アルトワークス(HA22S/HA23S) | D80: LINKECU | E80: 振り返り前回STEP20-1ではLINKECU製 CAN Lambdaの設定方法を紹介しました。 | F80: https://note.com/labratory_ktech/n/n4c98c460c771 | G80: altoworks-linkecu-step20-1-b728df, altoworks-linkecu-step21-891849 | H80: 2025-06-15 | I80: STEP本編（フルコン化手順） | J80: STEP20-2 | K80: アルトワークス フルコン化 HA22S事例/LINKECU 関連 | L80: #LINKECU #フルコン化 #ecuセッティング #HA22S #LINKECUセッティング #空燃比 #空燃比計 #Intenal #内部Lambda制御 #INTERNALLambda | M80: 100
A81: altoworks-linkecu-step20-1-b728df | B81: HA22S LINKECU フルコン化 STEP20-1 ワイドバンド空燃比入力 CAN Lambda編 | C81: アルトワークス(HA22S/HA23S) | D81: LINKECU | E81: 振り返り前回STEP19では燃料ポンプ制御をLINKECUで乗っ取りました(｀･ω･´) 今回はワイドバンド空燃比をLINKECUに取り込めるようにします。 | F81: https://note.com/labratory_ktech/n/nb5b138b728df | G81: altoworks-linkecu-step19-f71505, altoworks-linkecu-step20-2-60c771 | H81: 2025-06-15 | I81: STEP本編（フルコン化手順） | J81: STEP20-1 | K81: アルトワークス フルコン化 HA22S事例/LINKECU 関連/CAN 設定への道 | L81: #CAN #LINKECU #フルコン化 #HA22S #フルコンセッティング #LINKECUセッティング #ワイドバンド空燃比入力 | M81: 500
A82: altoworks-linkecu-step21-891849 | B82: HA22S LINKECU フルコン化 STEP21 AUX OUT 電動ファン制御 | C82: アルトワークス(HA22S/HA23S) | D82: LINKECU | E82: 振り返り前回STEP20-2ではLINKECU FURYのINTERNAL Lambdaセンサ駆動の配線と設定を紹介しました。 | F82: https://note.com/labratory_ktech/n/neafe19891849 | G82: altoworks-linkecu-step20-2-60c771, altoworks-linkecu-step22-6dba8f | H82: 2025-06-16 | I82: STEP本編（フルコン化手順） | J82: STEP21 | K82: アルトワークス フルコン化 HA22S事例/LINKECU 関連 | L82: #温度 #アルト #out #LINKECU #フルコン化 #HA22S #フルコンセッティング #LINKECUセッティング #aux #AUXOUT #ファン制御 #電動ファン制御 | M82: 100
A83: altoworks-linkecu-step22-6dba8f | B83: HA22S LINKECU フルコン化 STEP22 ABV撤去して！ | C83: アルトワークス(HA22S/HA23S) | D83: LINKECU | E83: 振り返り前回STEP21で電動ファンを動かしました。 | F83: https://note.com/labratory_ktech/n/n2414fe6dba8f | G83: altoworks-linkecu-step21-891849, altoworks-linkecu-step23-1-3786a0 | H83: 2025-06-18 | I83: STEP本編（フルコン化手順） | J83: STEP22 | K83: 新規格 K6A フルコン化情報/アルトワークス フルコン化 HA22S事例 | L83: #撤去 #ブースト #タービン #LINKECU #ソレノイド #HA22S #LINKECUセッティング #ブースト制御 #ABV | M83: 100
A84: porsche996-maxxecu-9cf152 | B84: PORSCHE 996 MaxxECU フルコン化 ACリクエストINPUT 躓きポイント 対策方法 | C84: Porsche996 | D84: MaxxECU | E84: Porsche 996ターボのプラグインECUがMaxxECUさんより、販売されています。 | F84: https://note.com/labratory_ktech/n/n81d4979cf152 | H84: 2025-06-19 | I84: CAN通信・周辺機器連携 | K84: CAN 設定への道/Porche 996フルコン化への道！ | L84: #ポルシェ #CAN #アドレス #porsche #canbus #996 #フルコン化 #MaxxECU #CAN設定 #エアコンリクエスト #躓きポイント #ACリクエストINPUT | M84: 20000
A85: altoworks-linkecu-step23-1-3786a0 | B85: HA22S LINKECU フルコン化 STEP23-1 AUX OUT WGソレノイド制御 ブースト制御 配線動作確認編 | C85: アルトワークス(HA22S/HA23S) | D85: LINKECU | E85: 振り返り前回STEP22ではABVの説明をしました。 | F85: https://note.com/labratory_ktech/n/nf57d113786a0 | G85: altoworks-linkecu-step22-6dba8f, altoworks-linkecu-step23-2-602c2f | H85: 2025-06-23 | I85: STEP本編（フルコン化手順） | J85: STEP23-1 | K85: 新規格 K6A フルコン化情報/アルトワークス フルコン化 HA22S事例 | L85: #ブースト #LINKECU #フルコン化 #ソレノイド #HA22S #ブースト制御 #ブーストコントロール #WGソレノイド制御 #配線動作確認編 #WG制御 | M85: 100
A86: copen-stockecu-c8903c | B86: L880K コペン Copen 後期 JB-DET 純正ECUピンアサイン エクセルファイル | C86: コペン(L880K) | D86: 純正ECU | E86: HA22S後期アルトワークスを事例にフルコン化作業を紹介しています。 | F86: https://note.com/labratory_ktech/n/nca70d9c8903c | H86: 2025-06-24 | I86: 配線・ピンアサイン資料 | K86: コペン L880K フルコン化 | M86: 1000
A87: altoworks-linkecu-step23-2-602c2f | B87: HA22S LINKECU フルコン化 STEP23-2 ブースト制御 WGアクチュエーター開弁圧調査 | C87: アルトワークス(HA22S/HA23S) | D87: LINKECU | E87: 振り返り前回STEP23-1ではWGソレノイドバルブの配線と動作確認の説明をしました。 | F87: https://note.com/labratory_ktech/n/n3a97ce602c2f | G87: altoworks-linkecu-step23-1-3786a0, altoworks-linkecu-step23-3-14b5b1 | H87: 2025-06-24 | I87: STEP本編（フルコン化手順） | J87: STEP23-2 | K87: （未分類） | M87: 300
A88: misc-linkecu-d21ba9 | B88: 吸気圧力センサの応答性についてLINKECU製 圧力センサって応答早いの？ | C88: （共通・車種特定なし） | D88: LINKECU | E88: LINKECU製や社外の圧力センサが高速応答で、純正センサなんて使ってられない！との発言しているのをよく聞きます。 | F88: https://note.com/labratory_ktech/n/n1868ddd21ba9 | H88: 2025-06-25 | I88: センサ・計測データ | K88: LINKECU 関連/ECUフルコン化への道/吸気圧力センサ 電圧-圧力特性測定結果 | L88: #センサ #LINKECU #圧力センサ #MAPセンサ #吸気圧力 #圧力電圧特性 | M88: 100
A89: roadster-linkecu-step3-35987a | B89: NB1 ロドスタ MaxxECU Race フルコン化 STEP3 MAPセンサ取り付け例 | C89: ロードスター(NB8/NB1) | D89: LINKECU/MaxxECU | E89: ふりかえりStep2でスロットルポジションセンサ信号を入力して校正を行いました。 | F89: https://note.com/labratory_ktech/n/ne97ba535987a | G89: roadster-maxxecu-step2-4b2212, roadster-maxxecu-step3-2-972e9b | H89: 2025-06-26 | I89: STEP本編（フルコン化手順） | J89: STEP3 | K89: NB8 NB1ロードスター MaxxECU フルコン化への道 | L89: #ロードスター #LINKECU #Race #Step3 #フルコン化 #MaxxECU #LINKECUセッティング #NB1 #ロドスタ #NB8 #NB6 #MAPセンサ取り付け例 #LINECU | M89: 100
A90: misc-linkecu-f3b55b | B90: PDM PMUってなんですか！？ | C90: （共通・車種特定なし） | D90: LINKECU/MaxxECU/ECUMaster(PMU/ADU/EMU)/MOTEC | E90: 「PDM」（Motec MaxxECU LINKECU）「PMU」（ECUMaster）は、 どちらも自動車やモータースポーツ、航空、産業機… | F90: https://note.com/labratory_ktech/n/n28ab65f3b55b | H90: 2025-07-01 | I90: CAN通信・周辺機器連携 | K90: ECUmaster PMU ADU関連 | L90: #PdM #LINKECU #PMU #ecuセッティング #MaxxECU #ECUmaster #MoTeC #電源制御 #リレーヒューズ | M90: 0
A91: altoworks-linkecu-step23-3-14b5b1 | B91: HA22S LINKECU フルコン化 STEP23-3 ブースト制御 OPENLOOP スロットル開度に応じたブースト制御 | C91: アルトワークス(HA22S/HA23S) | D91: LINKECU | E91: 振り返り前回STEP23-2ではWGアクチュエーターの開弁圧を測定してブースト制御開始点の設定が終わっています。 | F91: https://note.com/labratory_ktech/n/n699e4b14b5b1 | G91: altoworks-linkecu-step23-2-602c2f, altoworks-linkecu-step23-4-4c62dd | H91: 2025-07-01 | I91: STEP本編（フルコン化手順） | J91: STEP23-3 | K91: アルトワークス フルコン化 HA22S事例/LINKECU 関連 | L91: #設定 #アクセル #ブースト #HA22S #K6A #ワークス #ブースト制御 #ブーストコントロール #WGDuty #WGコントロール | M91: 100
A92: misc-linkecu-step1-fd6e1b | B92: ECUMaster PMU Step1 電源配線 と 通信確認 | C92: （共通・車種特定なし） | D92: LINKECU/MaxxECU/ECUMaster(PMU/ADU/EMU) | E92: ECUMasterの設定方法について解説していきます。 | F92: https://note.com/labratory_ktech/n/n7c06adfd6e1b | G92: misc-ecumaster-step1-1-6b4102, misc-linkecu-step1-c991d6 | H92: 2025-07-02 | I92: STEP本編（フルコン化手順） | J92: STEP1 | K92: ECUmaster PMU ADU関連 | L92: #PdM #アース #LINKECU #PMU #MaxxECU #フルコンセッティング #ECUmaster #電源配線 #通信確認 | M92: 0
A93: misc-linkecu-e09b51 | B93: ECU Master PMU テストボード と 課題 | C93: （共通・車種特定なし） | D93: LINKECU/MaxxECU/ECUMaster(PMU/ADU/EMU) | E93: テストボードって？ECUMaster PMUの動作確認＆デモ＆学習用にタイトル画像のテストボードを作っています。 | F93: https://note.com/labratory_ktech/n/n886526e09b51 | H93: 2025-07-02 | I93: CAN通信・周辺機器連携 | K93: ECUmaster PMU ADU関連 | L93: #課題 #PdM #canbus #LINKECU #PMU #MaxxECU #ECUmaster #keypad #CAN設定 #テストボード | M93: 0
A94: misc-ecumaster-da2605 | B94: ECUMaster PMU スイッチ入力 ACTIVE Lo 設定例 | C94: （共通・車種特定なし） | D94: ECUMaster(PMU/ADU/EMU) | E94: ふりかえりPMUに電源が入って、通信できるようになった状態で次にいきます。 | F94: https://note.com/labratory_ktech/n/nc224f0da2605 | H94: 2025-07-05 | I94: CAN通信・周辺機器連携 | K94: ECUmaster PMU ADU関連 | L94: #スイッチ #PdM #LO #Active #PMU #ecuセッティング #フルコンセッティング #ECUmaster #設定例 #スイッチ入力 | M94: 200
A95: misc-624e06 | B95: 出力制御の基礎 PWM制御とは？ | C95: （共通・車種特定なし） | E95: 出力の制御をする際にPWM制御が良く使われます。 | F95: https://note.com/labratory_ktech/n/n10b2cb624e06 | H95: 2025-07-07 | I95: 基礎知識・準備 | K95: LINKECU 関連/ECUフルコン化への道 | L95: #ecuセッティング #PWM #Duty #フルコンセッティング #モータ制御 #PWM周波数 #エクセル計算 #DUTY制御 | M95: 100
A96: misc-linkecu-73d80c | B96: ECUMaster PMU OUTPUT設定 スイッチONでACTIVE | C96: （共通・車種特定なし） | D96: LINKECU/ECUMaster(PMU/ADU/EMU) | E96: ふりかえりPMUに機械式スイッチを取り付けてスイッチインプットがアクティブになるようにしました。 | F96: https://note.com/labratory_ktech/n/n30896b73d80c | H96: 2025-07-10 | I96: CAN通信・周辺機器連携 | K96: ECUmaster PMU ADU関連 | L96: #PdM #電流 #配膳 #LINKECU #PMU #ECUmaster #定格電流 #OUTPUT設定 #スイッチONでACTIVE #スイッチインプット #リレー撤去 | M96: 100
A97: roadster-maxxecu-step3-2-972e9b | B97: NB1 ロドスタ MaxxECU Race フルコン化 STEP3-2 MAPセンサ設定 | C97: ロードスター(NB8/NB1) | D97: MaxxECU | E97: ふりかえりStep3でMAPセンサを取り付けました。 | F97: https://note.com/labratory_ktech/n/n819d27972e9b | G97: roadster-linkecu-step3-35987a, roadster-linkecu-step4-0a8136 | H97: 2025-07-14 | I97: STEP本編（フルコン化手順） | J97: STEP3-2 | K97: NB8 NB1ロードスター MaxxECU フルコン化への道 | L97: #センサ #Race #フルコン化 #ecuセッティング #MaxxECU #NB1 #ロドスタ #吸気圧力 #MAPセンサ設定 | M97: 0
A98: roadster-linkecu-step4-0a8136 | B98: NB1 ロドスタ MaxxECU Race フルコン化 STEP4 水温センサ設定 | C98: ロードスター(NB8/NB1) | D98: LINKECU/MaxxECU | E98: ふりかえりStep3-1 3-2でMAPセンサを取り付けて、設定ができました。 | F98: https://note.com/labratory_ktech/n/n3645480a8136 | G98: roadster-maxxecu-step3-2-972e9b, roadster-maxxecu-step5-e97e15 | H98: 2025-07-15 | I98: STEP本編（フルコン化手順） | J98: STEP4 | K98: NB8 NB1ロードスター MaxxECU フルコン化への道 | L98: #水温 #センサ #ECU #LINKECU #Race #フルコン化 #ecuセッティング #MaxxECU #NB1 #ロドスタ #水温センサ設定 | M98: 200
A99: altoworks-linkecu-step24-321bc0 | B99: HA22S LINKECU フルコン化 STEP24 エンジンチェックランプ CEライト LINK制御 | C99: アルトワークス(HA22S/HA23S) | D99: LINKECU | E99: 振り返り前回STEP23関連で、ブーストソレノイドの制御をして、ブーストコントロールができるようになりました。 | F99: https://note.com/labratory_ktech/n/nb731e7321bc0 | G99: altoworks-linkecu-step23-4-4c62dd, altoworks-linkecu-step25-e58f2a | H99: 2025-07-16 | I99: STEP本編（フルコン化手順） | J99: STEP24 | K99: アルトワークス フルコン化 HA22S事例/LINKECU 関連 | L99: #アルト #ECU #LINKECU #フルコン化 #ecuセッティング #HA22S #フルコンセッティング #エンジンチェックランプ #CEライト #LINK制御 | M99: 100
A100: altoworks-linkecu-40af5a | B100: LINKECU フルコン化 CEライト設定 LINKがエンジンチェックランプ を点灯する条件は？ | C100: アルトワークス(HA22S/HA23S) | D100: LINKECU | E100: HA22Sのセッティング例STEP24で、チェックランプの設定方法を紹介しました。 | F100: https://note.com/labratory_ktech/n/n33600240af5a | H100: 2025-07-17 | I100: 基礎知識・準備 | K100: アルトワークス フルコン化 HA22S事例/LINKECU 関連 | L100: #エラー #lambda #センサ #LINKECU #フルコン化 #HA22S #エンジンチェックランプ #チェックランプ #フォルト | M100: 0
...

Sheet 車種展開_Pivot用
A1: 元slug | B1: 車種 | C1: カテゴリ | D1: ECU | E1: STEP表記 | F1: STEP_L1 | G1: STEP_L2 | H1: STEP_L3 | I1: タイトル | J1: 公開日 | K1: 価格 | L1: マガジン名 | M1: note URL
A2: misc-84a7b3 | B2: （共通・車種特定なし） | C2: その他 | I2: 初めましてなのか、お久しぶりなのか？ | J2: 2025-02-18 | K2: 0 | L2: （未分類） | M2: https://note.com/labratory_ktech/n/nf4258784a7b3
A3: misc-linkecu-e865c2 | B3: （共通・車種特定なし） | C3: 基礎知識・準備 | D3: LINKECU | I3: 自動車 フルコン化に必要なモノ | J3: 2025-02-20 | K3: 0 | L3: ECUフルコン化への道 | M3: https://note.com/labratory_ktech/n/n192a1be865c2
A4: misc-228e07 | B4: （共通・車種特定なし） | C4: 基礎知識・準備 | I4: 安定化電源を使う理由 | J4: 2025-02-23 | K4: 0 | L4: ECUフルコン化への道 | M4: https://note.com/labratory_ktech/n/nfe3377228e07
A5: misc-linkecu-6aecda | B5: （共通・車種特定なし） | C5: 基礎知識・準備 | D5: LINKECU/MaxxECU/MOTEC/EMTRON/Haltech | I5: フルコン勉強にお勧めのECUは？ | J5: 2025-02-24 | K5: 0 | L5: ECUフルコン化への道 | M5: https://note.com/labratory_ktech/n/n9881036aecda
A6: misc-linkecu-160fa8 | B6: （共通・車種特定なし） | C6: 基礎知識・準備 | D6: LINKECU | I6: 燃料セッティング 空燃比計とは？ | J6: 2025-02-26 | K6: 0 | L6: ECUフルコン化への道 | M6: https://note.com/labratory_ktech/n/n182b31160fa8
A7: misc-linkecu-711682 | B7: （共通・車種特定なし） | C7: 基礎知識・準備 | D7: LINKECU/MaxxECU | I7: 初心者？がECUフルコンを選定するのに一番大事なこと | J7: 2025-02-27 | K7: 0 | L7: ECUフルコン化への道 | M7: https://note.com/labratory_ktech/n/n612e8f711682
A8: misc-linkecu-275a47 | B8: （共通・車種特定なし） | C8: 他社ECU・機器情報 | D8: LINKECU/MaxxECU | I8: LINKECU MAXXECU どの機種選べばいいの？ | J8: 2025-03-01 | K8: 0 | L8: LINKECU 関連/MaxxECU フルコン化への道/ECUフルコン化への道 | M8: https://note.com/labratory_ktech/n/n5515d1275a47
A9: esse-cc2978 | B9: エッセ(ESSE) | C9: センサ・計測データ | I9: フルコン化の第１の壁 吸気圧力センサ特性どうやって測定するの？ | J9: 2025-03-02 | K9: 0 | L9: エッセ ESSE LINKECU フルコン化 への道/ECUフルコン化への道/吸気圧力センサ 電圧-圧力特性測定結果 | M9: https://note.com/labratory_ktech/n/n4fe44ccc2978
A10: fd3s-linkecu-774f15 | B10: FD3S(RX-7) | C10: 基礎知識・準備 | D10: LINKECU | I10: LINKECU PLUG IN FD3S 後期 電源供給 | J10: 2025-03-03 | K10: 0 | L10: LINKECU 関連/ECUフルコン化への道/FD3S LINKECU フルコン化への道 | M10: https://note.com/labratory_ktech/n/n4a4ba4774f15
A11: ae86-linkecu-460ba3 | B11: AE86 | C11: センサ・計測データ | D11: LINKECU/MaxxECU | I11: AE86 4AG 吸気圧力センサ特性 品番89421-12020 | J11: 2025-03-03 | K11: 2000 | L11: 吸気圧力センサ 電圧-圧力特性測定結果 | M11: https://note.com/labratory_ktech/n/n3b3112460ba3
A12: misc-linkecu-16c728 | B12: （共通・車種特定なし） | C12: 基礎知識・準備 | D12: LINKECU | I12: LINKECU 通電 と アンロック作業 | J12: 2025-03-03 | K12: 0 | L12: ECUフルコン化への道 | M12: https://note.com/labratory_ktech/n/n4a2c4616c728
A13: misc-8b7628 | B13: （共通・車種特定なし） | C13: センサ・計測データ | I13: AE92 4AG 吸気圧力センサ特性 品番 80420-20300 | J13: 2025-03-04 | K13: 2000 | L13: 吸気圧力センサ 電圧-圧力特性測定結果 | M13: https://note.com/labratory_ktech/n/nee83a58b7628
A14: misc-2b1b60 | B14: （共通・車種特定なし） | C14: 基礎知識・準備 | I14: フルコン化への道 ビギーバック配線とは？ | J14: 2025-03-05 | K14: 0 | L14: ECUフルコン化への道 | M14: https://note.com/labratory_ktech/n/n4a159e2b1b60
A15: altoworks-step0-4670ac | B15: アルトワークス(HA22S/HA23S) | C15: STEP本編（フルコン化手順） | E15: STEP0 | F15: 0 | I15: HA22Sフルコン化 STEP0 ECUピンアサイン | J15: 2025-03-08 | K15: 500 | L15: 新規格 K6A フルコン化情報/アルトワークス フルコン化 HA22S事例 | M15: https://note.com/labratory_ktech/n/na152494670ac
A16: altoworks-linkecu-step1-362693 | B16: アルトワークス(HA22S/HA23S) | C16: STEP本編（フルコン化手順） | D16: LINKECU | E16: STEP1 | F16: 1 | I16: HA22S K6A フルコン化 STEP1 ビギーバックハーネス | J16: 2025-03-08 | K16: 0 | L16: アルトワークス フルコン化 HA22S事例 | M16: https://note.com/labratory_ktech/n/ne2f733362693
A17: altoworks-linkecu-f776fe | B17: アルトワークス(HA22S/HA23S) | C17: 基礎知識・準備（車種別） | D17: LINKECU | I17: HA22S K6A アルトワークスフルコン化 | J17: 2025-03-08 | K17: 0 | L17: アルトワークス フルコン化 HA22S事例 | M17: https://note.com/labratory_ktech/n/n3eb953f776fe
A18: cappuccino-linkecu-e16ea7 | B18: カプチーノ(F6A) | C18: センサ・計測データ | D18: LINKECU | I18: F6A アルトカプチーノ 吸気圧力センサ特性 品番 18590-64D00 | J18: 2025-03-08 | K18: 3000 | L18: 吸気圧力センサ 電圧-圧力特性測定結果 | M18: https://note.com/labratory_ktech/n/neaa561e16ea7
A19: misc-2668a9 | B19: （共通・車種特定なし） | C19: センサ・計測データ | I19: インジェクター燃料圧力制御の基礎 燃料のリターン、リターンレスシステムとは？ | J19: 2025-03-08 | K19: 0 | L19: 燃料、インジェクター関連 無効噴射時間 | M19: https://note.com/labratory_ktech/n/n0f32362668a9
A20: altoworks-linkecu-step2-e48ff8 | B20: アルトワークス(HA22S/HA23S) | C20: STEP本編（フルコン化手順） | D20: LINKECU | E20: STEP2 | F20: 2 | I20: HA22S LINKECU フルコン化 STEP2 電源供給 | J20: 2025-03-09 | K20: 0 | L20: アルトワークス フルコン化 HA22S事例/ECUフルコン化への道 | M20: https://note.com/labratory_ktech/n/n3bb503e48ff8
A21: altoworks-b01abe | B21: アルトワークス(HA22S/HA23S) | C21: 基礎知識・準備 | I21: 温度センサ校正の基礎知識 分圧とは？ | J21: 2025-03-10 | K21: 0 | L21: アルトワークス フルコン化 HA22S事例/ECUフルコン化への道 | M21: https://note.com/labratory_ktech/n/ne58f6db01abe
A22: altoworks-linkecu-step3-ff1549 | B22: アルトワークス(HA22S/HA23S) | C22: STEP本編（フルコン化手順） | D22: LINKECU | E22: STEP3 | F22: 3 | I22: HA22S フルコン化 STEP3 スロットル信号入力とアナログ入力エラー設定の観点 | J22: 2025-03-11 | K22: 100 | L22: アルトワークス フルコン化 HA22S事例/ECUフルコン化への道 | M22: https://note.com/labratory_ktech/n/n58a1cbff1549
A23: altoworks-075bb5 | B23: アルトワークス(HA22S/HA23S) | C23: 部品選定・レビュー | I23: HA22 温度センサー 温度-抵抗特性測定結果 | J23: 2025-03-13 | K23: 500 | L23: アルトワークス フルコン化 HA22S事例/HA22S 部品関連情報/温度センサ関連 | M23: https://note.com/labratory_ktech/n/n6cea0c075bb5
A24: misc-a2b1f2 | B24: （共通・車種特定なし） | C24: センサ・計測データ | I24: 温度センサの温度-抵抗特性 と B定数 | J24: 2025-03-13 | K24: 0 | L24: LINKECU 関連/温度センサ関連/ECUフルコン化への道 | M24: https://note.com/labratory_ktech/n/nf904daa2b1f2
A25: copen-linkecu-6815ae | B25: コペン(L880K) | C25: センサ・計測データ | D25: LINKECU | I25: JB-DET コペン 吸気圧力センサ 品番 89421-97201 特性測定結果 | J25: 2025-03-14 | K25: 2000 | L25: 吸気圧力センサ 電圧-圧力特性測定結果/コペン L880K フルコン化 | M25: https://note.com/labratory_ktech/n/nd325a66815ae
A26: altoworks-linkecu-91bebe | B26: アルトワークス(HA22S/HA23S) | C26: センサ・計測データ | D26: LINKECU | I26: HA22S 吸気圧力センサ HITACHI製 品番 18590-78G50 特性測定結果 | J26: 2025-03-15 | K26: 2000 | L26: アルトワークス フルコン化 HA22S事例/吸気圧力センサ 電圧-圧力特性測定結果 | M26: https://note.com/labratory_ktech/n/n6cfee691bebe
A27: altoworks-linkecu-step4-ceb9fa | B27: アルトワークス(HA22S/HA23S) | C27: STEP本編（フルコン化手順） | D27: LINKECU | E27: STEP4 | F27: 4 | I27: HA22S フルコン化 STEP4 吸気圧力信号入力 と センサCaliblation設定の観点 | J27: 2025-03-16 | K27: 0 | L27: アルトワークス フルコン化 HA22S事例/ECUフルコン化への道 | M27: https://note.com/labratory_ktech/n/nb5f07fceb9fa
A28: altoworks-linkecu-b980ee | B28: アルトワークス(HA22S/HA23S) | C28: その他 | D28: LINKECU | I28: HA23 吸気圧力センサ Denso製 品番 18590-79F00 特性測定結果 | J28: 2025-03-16 | K28: 2000 | L28: （未分類） | M28: https://note.com/labratory_ktech/n/n0c63cbb980ee
A29: misc-26b3d3 | B29: （共通・車種特定なし） | C29: センサ・計測データ | I29: 燃料圧力と噴射量の関係性 | J29: 2025-03-17 | K29: 0 | L29: 燃料、インジェクター関連 無効噴射時間/ECUフルコン化への道 | M29: https://note.com/labratory_ktech/n/n57277926b3d3
A30: misc-bb3fb4 | B30: （共通・車種特定なし） | C30: センサ・計測データ | I30: インジェクタ流量と馬力の関係 | J30: 2025-03-18 | K30: 200 | L30: 燃料、インジェクター関連 無効噴射時間/ECUフルコン化への道 | M30: https://note.com/labratory_ktech/n/n5809cebb3fb4
A31: misc-linkecu-922d25 | B31: （共通・車種特定なし） | C31: 配線・ピンアサイン資料 | D31: LINKECU | I31: TA-HE21S ラパンSS 純正ECUピンアサイン エクセルファイル | J31: 2025-03-19 | K31: 5000 | L31: 新規格 K6A フルコン化情報 | M31: https://note.com/labratory_ktech/n/n959df6922d25
A32: misc-6a1297 | B32: （共通・車種特定なし） | C32: センサ・計測データ | I32: HN12等 F6A ターボ 吸気圧力センサ Denso製 品番 18590-76G50 特性測定結果 | J32: 2025-03-21 | K32: 2000 | L32: 吸気圧力センサ 電圧-圧力特性測定結果 | M32: https://note.com/labratory_ktech/n/n3cf1366a1297
A33: misc-motec-4c23e9 | B33: （共通・車種特定なし） | C33: センサ・計測データ | D33: MOTEC | I33: GM MAP SENSOR | J33: 2025-03-21 | K33: 0 | L33: 吸気圧力センサ 電圧-圧力特性測定結果 | M33: https://note.com/labratory_ktech/n/n966de44c23e9
A34: misc-linkecu-733713 | B34: （共通・車種特定なし） | C34: センサ・計測データ | D34: LINKECU | I34: 温度センサ校正の基礎 LINKECU例 プルアップ抵抗 有り編 | J34: 2025-03-23 | K34: 0 | L34: LINKECU 関連/温度センサ関連 | M34: https://note.com/labratory_ktech/n/n8e1736733713
A35: misc-linkecu-451883 | B35: （共通・車種特定なし） | C35: センサ・計測データ | D35: LINKECU | I35: 温度センサ校正の基礎 LINKECU例 プルアップ抵抗OFF ビギーバック編 | J35: 2025-03-25 | K35: 500 | L35: LINKECU 関連/温度センサ関連/ECUフルコン化への道 | M35: https://note.com/labratory_ktech/n/n0085d3451883
A36: misc-linkecu-1d2d43 | B36: （共通・車種特定なし） | C36: 部品選定・レビュー | D36: LINKECU | I36: SARD1000cc/min 低抵抗 インジェクター | J36: 2025-03-27 | K36: 0 | L36: 車関係部品 写真置き場 | M36: https://note.com/labratory_ktech/n/nfb525f1d2d43
A37: misc-linkecu-660efd | B37: （共通・車種特定なし） | C37: センサ・計測データ | D37: LINKECU | I37: 1JZ 2JZ 等 ターボ用 吸気圧力センサ Denso製 品番 89421-12111 特性測定結果 | J37: 2025-03-29 | K37: 2000 | L37: 吸気圧力センサ 電圧-圧力特性測定結果 | M37: https://note.com/labratory_ktech/n/n9b53de660efd
A38: altoworks-linkecu-step5-e41aba | B38: アルトワークス(HA22S/HA23S) | C38: STEP本編（フルコン化手順） | D38: LINKECU | E38: STEP5 | F38: 5 | I38: HA22S フルコン化 STEP5 温度センサ校正設定 | J38: 2025-03-29 | K38: 2000 | L38: 新規格 K6A フルコン化情報/アルトワークス フルコン化 HA22S事例/温度センサ関連 | M38: https://note.com/labratory_ktech/n/ne1c5b4e41aba
A39: misc-emanage-191520 | B39: （共通・車種特定なし） | C39: センサ・計測データ | D39: E-manage | I39: TRUST e-manage オプション 吸気圧力センサ 特性測定結果 | J39: 2025-03-30 | K39: 1000 | L39: 吸気圧力センサ 電圧-圧力特性測定結果 | M39: https://note.com/labratory_ktech/n/ndaf171191520
A40: misc-linkecu-575188 | B40: （共通・車種特定なし） | C40: 配線・ピンアサイン資料 | D40: LINKECU | I40: MC21S K6A ワゴンR 純正ECUピンアサイン エクセルファイル | J40: 2025-03-30 | K40: 2000 | L40: 新規格 K6A フルコン化情報 | M40: https://note.com/labratory_ktech/n/n522bbf575188
A41: altoworks-linkecu-step6-888601 | B41: アルトワークス(HA22S/HA23S) | C41: STEP本編（フルコン化手順） | D41: LINKECU | E41: STEP6 | F41: 6 | I41: HA22S フルコン化 STEP6 回転数トリガ設定 | J41: 2025-03-30 | K41: 100 | L41: アルトワークス フルコン化 HA22S事例/ECUフルコン化への道 | M41: https://note.com/labratory_ktech/n/nb50b3a888601
A42: altoworks-linkecu-step7-3a2b38 | B42: アルトワークス(HA22S/HA23S) | C42: STEP本編（フルコン化手順） | D42: LINKECU | E42: STEP7 | F42: 7 | I42: HA22S フルコン化 STEP7 エンジン設定 | J42: 2025-04-02 | K42: 0 | L42: 新規格 K6A フルコン化情報/アルトワークス フルコン化 HA22S事例 | M42: https://note.com/labratory_ktech/n/n051d663a2b38
A43: misc-linkecu-b13f31 | B43: （共通・車種特定なし） | C43: センサ・計測データ | D43: LINKECU | I43: ラパンSS 他 水温アラーム制御方法 | J43: 2025-04-07 | K43: 3000 | L43: 新規格 K6A フルコン化情報/温度センサ関連 | M43: https://note.com/labratory_ktech/n/n146db3b13f31
A44: porsche996-e0ad62 | B44: Porsche996 | C44: センサ・計測データ | I44: Porche 996 Turbo Bosch T-MAP Sensor 0 261 230 042 特性測定結果 | J44: 2025-04-08 | K44: 10000 | L44: 吸気圧力センサ 電圧-圧力特性測定結果/Porche 996フルコン化への道！ | M44: https://note.com/labratory_ktech/n/nc98c88e0ad62
A45: misc-linkecu-499cb9 | B45: （共通・車種特定なし） | C45: センサ・計測データ | D45: LINKECU/MaxxECU | I45: エンジン回転数と周波数 周期サイクルタイムの関係性 | J45: 2025-04-09 | K45: 200 | L45: 燃料、インジェクター関連 無効噴射時間/ECUフルコン化への道 | M45: https://note.com/labratory_ktech/n/n16bbf9499cb9
A46: misc-linkecu-9b257b | B46: （共通・車種特定なし） | C46: センサ・計測データ | D46: LINKECU/MaxxECU | I46: 計測器 8CH オシロスコープ HANTECH 1008C | J46: 2025-04-11 | K46: 0 | L46: 計測器情報/ECUフルコン化への道 | M46: https://note.com/labratory_ktech/n/n9eda7c9b257b
A47: cappuccino-linkecu-step0-929164 | B47: カプチーノ(F6A) | C47: STEP本編（フルコン化手順） | D47: LINKECU/MaxxECU | E47: STEP0 | F47: 0 | I47: カプチーノフルコン化 STEP0 EA11 F6A 純正ECUピンアサイン エクセルファイル | J47: 2025-04-12 | K47: 2000 | L47: F6A カプチーノフルコン化への道 | M47: https://note.com/labratory_ktech/n/n383740929164
A48: misc-83caf9 | B48: （共通・車種特定なし） | C48: 基礎知識・準備 | I48: 点火イグニッションコイルとイグナイターの有無について | J48: 2025-04-13 | K48: 0 | L48: ECUフルコン化への道 | M48: https://note.com/labratory_ktech/n/nf6f30283caf9
A49: misc-linkecu-1999b2 | B49: （共通・車種特定なし） | C49: 基礎知識・準備 | D49: LINKECU | I49: 卓上点火テスト板 製作 | J49: 2025-04-14 | K49: 0 | L49: ECUフルコン化への道 | M49: https://note.com/labratory_ktech/n/n3ed4371999b2
A50: altoworks-linkecu-step8-a28e89 | B50: アルトワークス(HA22S/HA23S) | C50: STEP本編（フルコン化手順） | D50: LINKECU | E50: STEP8 | F50: 8 | I50: HA22S フルコン化 STEP8 点火テスト | J50: 2025-04-22 | K50: 0 | L50: アルトワークス フルコン化 HA22S事例 | M50: https://note.com/labratory_ktech/n/n2c4e23a28e89
A51: misc-linkecu-5d19f6 | B51: （共通・車種特定なし） | C51: センサ・計測データ | D51: LINKECU | I51: イグニッション・ドエルタイム（Dwell Time）とは？ | J51: 2025-04-24 | K51: 500 | L51: ECUフルコン化への道/点火コイル Dwell timeまとめ | M51: https://note.com/labratory_ktech/n/n3d98615d19f6
A52: misc-linkecu-9d34ab | B52: （共通・車種特定なし） | C52: センサ・計測データ | D52: LINKECU | I52: 市販メータを使った 圧力センサ校正をする際の注意点 | J52: 2025-04-29 | K52: 500 | L52: ECUフルコン化への道/吸気圧力センサ 電圧-圧力特性測定結果 | M52: https://note.com/labratory_ktech/n/na067499d34ab
A53: misc-7bd62b | B53: （共通・車種特定なし） | C53: 部品選定・レビュー | I53: ※注意：バッテリーカットターミナル付けたままスポーツ走行しないで！！！ | J53: 2025-05-01 | K53: 0 | L53: パーツレビュー | M53: https://note.com/labratory_ktech/n/n5ff81c7bd62b
A54: altoworks-linkecu-step9-6e88d5 | B54: アルトワークス(HA22S/HA23S) | C54: STEP本編（フルコン化手順） | D54: LINKECU | E54: STEP9 | F54: 9 | I54: HA22S フルコン化 STEP9 点火基準合わせ | J54: 2025-05-03 | K54: 500 | L54: アルトワークス フルコン化 HA22S事例/ECUフルコン化への道 | M54: https://note.com/labratory_ktech/n/n0042b76e88d5
A55: cappuccino-4c7d9b | B55: カプチーノ(F6A) | C55: 配線・ピンアサイン資料 | I55: カプチーノ F6A エアコン制御基板 ピンアサイン | J55: 2025-05-08 | K55: 1000 | L55: F6A カプチーノフルコン化への道 | M55: https://note.com/labratory_ktech/n/n4fd2474c7d9b
A56: misc-99eb44 | B56: （共通・車種特定なし） | C56: センサ・計測データ | I56: ガスコイル コイルベンチマーク測定結果 | J56: 2025-05-13 | K56: 2000 | L56: 点火コイル Dwell timeまとめ | M56: https://note.com/labratory_ktech/n/nacb87d99eb44
A57: misc-linkecu-759452 | B57: （共通・車種特定なし） | C57: センサ・計測データ | D57: LINKECU | I57: 点火コイルの Dwell time 測定用 コイルベンチマーク | J57: 2025-05-13 | K57: 1000 | L57: ECUフルコン化への道/点火コイル Dwell timeまとめ | M57: https://note.com/labratory_ktech/n/nab4ec5759452
A58: misc-81c254 | B58: （共通・車種特定なし） | C58: センサ・計測データ | I58: EJ207 GC8 同時点火コイル コイルベンチマーク測定結果 | J58: 2025-05-14 | K58: 2000 | L58: 点火コイル Dwell timeまとめ | M58: https://note.com/labratory_ktech/n/ne0308281c254
A59: altoworks-linkecu-step10-8958ff | B59: アルトワークス(HA22S/HA23S) | C59: STEP本編（フルコン化手順） | D59: LINKECU | E59: STEP10 | F59: 10 | I59: HA22S LINKECU フルコン化 STEP10 車速入力 | J59: 2025-05-21 | K59: 100 | L59: 新規格 K6A フルコン化情報/アルトワークス フルコン化 HA22S事例 | M59: https://note.com/labratory_ktech/n/na48afe8958ff
A60: misc-linkecu-step1-c991d6 | B60: （共通・車種特定なし） | C60: STEP本編（フルコン化手順） | D60: LINKECU/MaxxECU | E60: STEP1 | F60: 1 | I60: CAN通信への道 STEP1 CAN信号送受信 | J60: 2025-05-22 | K60: 0 | L60: CAN 設定への道/ECUフルコン化への道 | M60: https://note.com/labratory_ktech/n/n632aa0c991d6
A61: altoworks-linkecu-step11-7d733e | B61: アルトワークス(HA22S/HA23S) | C61: STEP本編（フルコン化手順） | D61: LINKECU | E61: STEP11 | F61: 11 | I61: HA22S LINKECU フルコン化 STEP11 ギヤ認識 | J61: 2025-05-23 | K61: 200 | L61: アルトワークス フルコン化 HA22S事例/ECUフルコン化への道 | M61: https://note.com/labratory_ktech/n/n072b717d733e
A62: misc-linkecu-13b0e6 | B62: （共通・車種特定なし） | C62: CAN通信・周辺機器連携 | D62: LINKECU/ECUMaster(PMU/ADU/EMU) | I62: ECUMaster USB to CAN 使用手順と注意点 | J62: 2025-05-23 | K62: 200 | L62: CAN 設定への道/ECUフルコン化への道/ECUmaster PMU ADU関連 | M62: https://note.com/labratory_ktech/n/n6668d413b0e6
A63: misc-linkecu-2cbddc | B63: （共通・車種特定なし） | C63: CAN通信・周辺機器連携 | D63: LINKECU/ECUMaster(PMU/ADU/EMU) | I63: ECUmaster ADU アナログ入力 ギヤ設定 | J63: 2025-05-27 | K63: 1000 | L63: ECUmaster PMU ADU関連 | M63: https://note.com/labratory_ktech/n/n5aa5f82cbddc
A64: altoworks-linkecu-6e5875 | B64: アルトワークス(HA22S/HA23S) | C64: 基礎知識・準備 | D64: LINKECU | I64: スイッチ入力の基礎 Hisideインプット Losideインプット プルアップ抵抗 プルダウン抵抗 | J64: 2025-06-01 | K64: 500 | L64: アルトワークス フルコン化 HA22S事例/ECUフルコン化への道 | M64: https://note.com/labratory_ktech/n/nc8a5ba6e5875
A65: fd3s-linkecu-110900 | B65: FD3S(RX-7) | C65: センサ・計測データ | D65: LINKECU | I65: RX-7 FD3S 吸気圧力センサ特性 品番N3A1-18-211 100798-2131 | J65: 2025-06-03 | K65: 2000 | L65: 吸気圧力センサ 電圧-圧力特性測定結果 | M65: https://note.com/labratory_ktech/n/n9f7f14110900
A66: altoworks-linkecu-step12-1cdbb0 | B66: アルトワークス(HA22S/HA23S) | C66: STEP本編（フルコン化手順） | D66: LINKECU | E66: STEP12 | F66: 12 | I66: HA22S LINKECU フルコン化 STEP12 デジタルインプット 電気負荷信号入力 | J66: 2025-06-04 | K66: 100 | L66: アルトワークス フルコン化 HA22S事例 | M66: https://note.com/labratory_ktech/n/n7c61e01cdbb0
A67: misc-linkecu-6e0042 | B67: （共通・車種特定なし） | C67: 他社ECU・機器情報 | D67: LINKECU/MaxxECU | I67: MaxxECU フルコン化への道 始まるよ！ | J67: 2025-06-05 | K67: 200 | L67: MaxxECU フルコン化への道 | M67: https://note.com/labratory_ktech/n/n5531386e0042
A68: roadster-maxxecu-eb9512 | B68: ロードスター(NB8/NB1) | C68: 配線・ピンアサイン資料 | D68: MaxxECU | I68: NB1 フルコン化への道 ECUピンアサイン | J68: 2025-06-07 | K68: 1000 | L68: NB8 NB1ロードスター MaxxECU フルコン化への道 | M68: https://note.com/labratory_ktech/n/n53461beb9512
A69: altoworks-linkecu-step13-0eae4c | B69: アルトワークス(HA22S/HA23S) | C69: STEP本編（フルコン化手順） | D69: LINKECU | E69: STEP13 | F69: 13 | I69: HA22S LINKECU フルコン化 STEP13 デジタルインプット ブロアファン信号入力 | J69: 2025-06-07 | K69: 100 | L69: アルトワークス フルコン化 HA22S事例 | M69: https://note.com/labratory_ktech/n/n21ee0a0eae4c
A70: roadster-maxxecu-773dd4 | B70: ロードスター(NB8/NB1) | C70: 他社ECU・機器情報 | D70: MaxxECU | I70: MaxxECUフルコン化 まず始めの作業 電源供給 と ソフトウェアダウンロード | J70: 2025-06-08 | K70: 100 | L70: MaxxECU フルコン化への道/NB8 NB1ロードスター MaxxECU フルコン化への道 | M70: https://note.com/labratory_ktech/n/ne89913773dd4
A71: altoworks-linkecu-step14-4613b9 | B71: アルトワークス(HA22S/HA23S) | C71: STEP本編（フルコン化手順） | D71: LINKECU | E71: STEP14 | F71: 14 | I71: HA22S LINKECU フルコン化 STEP14 デジタルインプット エアコンリクエスト信号入力 | J71: 2025-06-09 | K71: 100 | L71: アルトワークス フルコン化 HA22S事例 | M71: https://note.com/labratory_ktech/n/n23416a4613b9
A72: altoworks-linkecu-step15-7877b4 | B72: アルトワークス(HA22S/HA23S) | C72: STEP本編（フルコン化手順） | D72: LINKECU | E72: STEP15 | F72: 15 | I72: HA22S LINKECU フルコン化 STEP15 デジタルインプット イグニッションKeyON 信号入力 ECU Holdパワーの準備 | J72: 2025-06-10 | K72: 100 | L72: 新規格 K6A フルコン化情報/アルトワークス フルコン化 HA22S事例/ECUフルコン化への道 | M72: https://note.com/labratory_ktech/n/nda6c7b7877b4
A73: altoworks-linkecu-step16-afcadf | B73: アルトワークス(HA22S/HA23S) | C73: STEP本編（フルコン化手順） | D73: LINKECU | E73: STEP16 | F73: 16 | I73: HA22S LINKECU フルコン化 STEP16 デジタルインプット ブレーキスイッチ 信号入力 | J73: 2025-06-11 | K73: 100 | L73: 新規格 K6A フルコン化情報/アルトワークス フルコン化 HA22S事例 | M73: https://note.com/labratory_ktech/n/n117100afcadf
A74: altoworks-linkecu-step17-c86c82 | B74: アルトワークス(HA22S/HA23S) | C74: STEP本編（フルコン化手順） | D74: LINKECU | E74: STEP17 | F74: 17 | I74: HA22S LINKECU フルコン化 STEP17 アナログ入力 O2センサー Lambda 信号入力 | J74: 2025-06-13 | K74: 100 | L74: 新規格 K6A フルコン化情報/アルトワークス フルコン化 HA22S事例 | M74: https://note.com/labratory_ktech/n/n36e113c86c82
A75: altoworks-linkecu-step19-f71505 | B75: アルトワークス(HA22S/HA23S) | C75: STEP本編（フルコン化手順） | D75: LINKECU | E75: STEP19 | F75: 19 | I75: HA22S LINKECU フルコン化 STEP19 Aux出力 燃料ポンプリレー制御 | J75: 2025-06-14 | K75: 100 | L75: アルトワークス フルコン化 HA22S事例/LINKECU 関連 | M75: https://note.com/labratory_ktech/n/n94ab9bf71505
A76: altoworks-linkecu-step18-468088 | B76: アルトワークス(HA22S/HA23S) | C76: STEP本編（フルコン化手順） | D76: LINKECU | E76: STEP18 | F76: 18 | I76: HA22S LINKECU フルコン化 STEP18 Aux出力 タコメータ制御 | J76: 2025-06-14 | K76: 100 | L76: アルトワークス フルコン化 HA22S事例/LINKECU 関連 | M76: https://note.com/labratory_ktech/n/nbe600c468088
A77: fd3s-linkecu-786b87 | B77: FD3S(RX-7) | C77: 基礎知識・準備（車種別） | D77: LINKECU/Apexi PowerFC | I77: FD3S FC3S アペックス パワーFC ECU内温度センサ入力のプルアップ抵抗っていくつやねん！ | J77: 2025-06-14 | K77: 500 | L77: FD3S LINKECU フルコン化への道 | M77: https://note.com/labratory_ktech/n/ne6a076786b87
A78: roadster-maxxecu-step2-4b2212 | B78: ロードスター(NB8/NB1) | C78: STEP本編（フルコン化手順） | D78: MaxxECU | E78: STEP2 | F78: 2 | I78: NB1 ロドスタ ロードスター MaxxECU Race フルコン化 STEP2 スロットルポジションセンサ 信号入力 アナログインプット | J78: 2025-06-14 | K78: 100 | L78: MaxxECU フルコン化への道/NB8 NB1ロードスター MaxxECU フルコン化への道 | M78: https://note.com/labratory_ktech/n/n00d2384b2212
A79: roadster-maxxecu-step1-be4007 | B79: ロードスター(NB8/NB1) | C79: STEP本編（フルコン化手順） | D79: MaxxECU | E79: STEP1 | F79: 1 | I79: NB1 ロドスタ MaxxECU Race フルコン化 STEP1 電源配線 | J79: 2025-06-14 | K79: 0 | L79: NB8 NB1ロードスター MaxxECU フルコン化への道 | M79: https://note.com/labratory_ktech/n/nd4c40cbe4007
A80: altoworks-linkecu-step20-2-60c771 | B80: アルトワークス(HA22S/HA23S) | C80: STEP本編（フルコン化手順） | D80: LINKECU | E80: STEP20-2 | F80: 20 | G80: 2 | I80: HA22S LINKECU フルコン化 STEP20-2ワイドバンド空燃比入力 Intenal Lambda制御編（Fury） | J80: 2025-06-15 | K80: 100 | L80: アルトワークス フルコン化 HA22S事例/LINKECU 関連 | M80: https://note.com/labratory_ktech/n/n4c98c460c771
A81: altoworks-linkecu-step20-1-b728df | B81: アルトワークス(HA22S/HA23S) | C81: STEP本編（フルコン化手順） | D81: LINKECU | E81: STEP20-1 | F81: 20 | G81: 1 | I81: HA22S LINKECU フルコン化 STEP20-1 ワイドバンド空燃比入力 CAN Lambda編 | J81: 2025-06-15 | K81: 500 | L81: アルトワークス フルコン化 HA22S事例/LINKECU 関連/CAN 設定への道 | M81: https://note.com/labratory_ktech/n/nb5b138b728df
A82: altoworks-linkecu-step21-891849 | B82: アルトワークス(HA22S/HA23S) | C82: STEP本編（フルコン化手順） | D82: LINKECU | E82: STEP21 | F82: 21 | I82: HA22S LINKECU フルコン化 STEP21 AUX OUT 電動ファン制御 | J82: 2025-06-16 | K82: 100 | L82: アルトワークス フルコン化 HA22S事例/LINKECU 関連 | M82: https://note.com/labratory_ktech/n/neafe19891849
A83: altoworks-linkecu-step22-6dba8f | B83: アルトワークス(HA22S/HA23S) | C83: STEP本編（フルコン化手順） | D83: LINKECU | E83: STEP22 | F83: 22 | I83: HA22S LINKECU フルコン化 STEP22 ABV撤去して！ | J83: 2025-06-18 | K83: 100 | L83: 新規格 K6A フルコン化情報/アルトワークス フルコン化 HA22S事例 | M83: https://note.com/labratory_ktech/n/n2414fe6dba8f
A84: porsche996-maxxecu-9cf152 | B84: Porsche996 | C84: CAN通信・周辺機器連携 | D84: MaxxECU | I84: PORSCHE 996 MaxxECU フルコン化 ACリクエストINPUT 躓きポイント 対策方法 | J84: 2025-06-19 | K84: 20000 | L84: CAN 設定への道/Porche 996フルコン化への道！ | M84: https://note.com/labratory_ktech/n/n81d4979cf152
A85: altoworks-linkecu-step23-1-3786a0 | B85: アルトワークス(HA22S/HA23S) | C85: STEP本編（フルコン化手順） | D85: LINKECU | E85: STEP23-1 | F85: 23 | G85: 1 | I85: HA22S LINKECU フルコン化 STEP23-1 AUX OUT WGソレノイド制御 ブースト制御 配線動作確認編 | J85: 2025-06-23 | K85: 100 | L85: 新規格 K6A フルコン化情報/アルトワークス フルコン化 HA22S事例 | M85: https://note.com/labratory_ktech/n/nf57d113786a0
A86: copen-stockecu-c8903c | B86: コペン(L880K) | C86: 配線・ピンアサイン資料 | D86: 純正ECU | I86: L880K コペン Copen 後期 JB-DET 純正ECUピンアサイン エクセルファイル | J86: 2025-06-24 | K86: 1000 | L86: コペン L880K フルコン化 | M86: https://note.com/labratory_ktech/n/nca70d9c8903c
A87: altoworks-linkecu-step23-2-602c2f | B87: アルトワークス(HA22S/HA23S) | C87: STEP本編（フルコン化手順） | D87: LINKECU | E87: STEP23-2 | F87: 23 | G87: 2 | I87: HA22S LINKECU フルコン化 STEP23-2 ブースト制御 WGアクチュエーター開弁圧調査 | J87: 2025-06-24 | K87: 300 | L87: （未分類） | M87: https://note.com/labratory_ktech/n/n3a97ce602c2f
A88: misc-linkecu-d21ba9 | B88: （共通・車種特定なし） | C88: センサ・計測データ | D88: LINKECU | I88: 吸気圧力センサの応答性についてLINKECU製 圧力センサって応答早いの？ | J88: 2025-06-25 | K88: 100 | L88: LINKECU 関連/ECUフルコン化への道/吸気圧力センサ 電圧-圧力特性測定結果 | M88: https://note.com/labratory_ktech/n/n1868ddd21ba9
A89: roadster-linkecu-step3-35987a | B89: ロードスター(NB8/NB1) | C89: STEP本編（フルコン化手順） | D89: LINKECU/MaxxECU | E89: STEP3 | F89: 3 | I89: NB1 ロドスタ MaxxECU Race フルコン化 STEP3 MAPセンサ取り付け例 | J89: 2025-06-26 | K89: 100 | L89: NB8 NB1ロードスター MaxxECU フルコン化への道 | M89: https://note.com/labratory_ktech/n/ne97ba535987a
A90: misc-linkecu-f3b55b | B90: （共通・車種特定なし） | C90: CAN通信・周辺機器連携 | D90: LINKECU/MaxxECU/ECUMaster(PMU/ADU/EMU)/MOTEC | I90: PDM PMUってなんですか！？ | J90: 2025-07-01 | K90: 0 | L90: ECUmaster PMU ADU関連 | M90: https://note.com/labratory_ktech/n/n28ab65f3b55b
A91: altoworks-linkecu-step23-3-14b5b1 | B91: アルトワークス(HA22S/HA23S) | C91: STEP本編（フルコン化手順） | D91: LINKECU | E91: STEP23-3 | F91: 23 | G91: 3 | I91: HA22S LINKECU フルコン化 STEP23-3 ブースト制御 OPENLOOP スロットル開度に応じたブースト制御 | J91: 2025-07-01 | K91: 100 | L91: アルトワークス フルコン化 HA22S事例/LINKECU 関連 | M91: https://note.com/labratory_ktech/n/n699e4b14b5b1
A92: misc-linkecu-step1-fd6e1b | B92: （共通・車種特定なし） | C92: STEP本編（フルコン化手順） | D92: LINKECU/MaxxECU/ECUMaster(PMU/ADU/EMU) | E92: STEP1 | F92: 1 | I92: ECUMaster PMU Step1 電源配線 と 通信確認 | J92: 2025-07-02 | K92: 0 | L92: ECUmaster PMU ADU関連 | M92: https://note.com/labratory_ktech/n/n7c06adfd6e1b
A93: misc-linkecu-e09b51 | B93: （共通・車種特定なし） | C93: CAN通信・周辺機器連携 | D93: LINKECU/MaxxECU/ECUMaster(PMU/ADU/EMU) | I93: ECU Master PMU テストボード と 課題 | J93: 2025-07-02 | K93: 0 | L93: ECUmaster PMU ADU関連 | M93: https://note.com/labratory_ktech/n/n886526e09b51
A94: misc-ecumaster-da2605 | B94: （共通・車種特定なし） | C94: CAN通信・周辺機器連携 | D94: ECUMaster(PMU/ADU/EMU) | I94: ECUMaster PMU スイッチ入力 ACTIVE Lo 設定例 | J94: 2025-07-05 | K94: 200 | L94: ECUmaster PMU ADU関連 | M94: https://note.com/labratory_ktech/n/nc224f0da2605
A95: misc-624e06 | B95: （共通・車種特定なし） | C95: 基礎知識・準備 | I95: 出力制御の基礎 PWM制御とは？ | J95: 2025-07-07 | K95: 100 | L95: LINKECU 関連/ECUフルコン化への道 | M95: https://note.com/labratory_ktech/n/n10b2cb624e06
A96: misc-linkecu-73d80c | B96: （共通・車種特定なし） | C96: CAN通信・周辺機器連携 | D96: LINKECU/ECUMaster(PMU/ADU/EMU) | I96: ECUMaster PMU OUTPUT設定 スイッチONでACTIVE | J96: 2025-07-10 | K96: 100 | L96: ECUmaster PMU ADU関連 | M96: https://note.com/labratory_ktech/n/n30896b73d80c
A97: roadster-maxxecu-step3-2-972e9b | B97: ロードスター(NB8/NB1) | C97: STEP本編（フルコン化手順） | D97: MaxxECU | E97: STEP3-2 | F97: 3 | G97: 2 | I97: NB1 ロドスタ MaxxECU Race フルコン化 STEP3-2 MAPセンサ設定 | J97: 2025-07-14 | K97: 0 | L97: NB8 NB1ロードスター MaxxECU フルコン化への道 | M97: https://note.com/labratory_ktech/n/n819d27972e9b
A98: roadster-linkecu-step4-0a8136 | B98: ロードスター(NB8/NB1) | C98: STEP本編（フルコン化手順） | D98: LINKECU/MaxxECU | E98: STEP4 | F98: 4 | I98: NB1 ロドスタ MaxxECU Race フルコン化 STEP4 水温センサ設定 | J98: 2025-07-15 | K98: 200 | L98: NB8 NB1ロードスター MaxxECU フルコン化への道 | M98: https://note.com/labratory_ktech/n/n3645480a8136
A99: altoworks-linkecu-step24-321bc0 | B99: アルトワークス(HA22S/HA23S) | C99: STEP本編（フルコン化手順） | D99: LINKECU | E99: STEP24 | F99: 24 | I99: HA22S LINKECU フルコン化 STEP24 エンジンチェックランプ CEライト LINK制御 | J99: 2025-07-16 | K99: 100 | L99: アルトワークス フルコン化 HA22S事例/LINKECU 関連 | M99: https://note.com/labratory_ktech/n/nb731e7321bc0
A100: altoworks-linkecu-40af5a | B100: アルトワークス(HA22S/HA23S) | C100: 基礎知識・準備 | D100: LINKECU | I100: LINKECU フルコン化 CEライト設定 LINKがエンジンチェックランプ を点灯する条件は？ | J100: 2025-07-17 | K100: 0 | L100: アルトワークス フルコン化 HA22S事例/LINKECU 関連 | M100: https://note.com/labratory_ktech/n/n33600240af5a
...

Sheet 車種×カテゴリ集計
A1: 車種＼カテゴリ | B1: STEP本編（フルコン化手順） | C1: 基礎知識・準備 | D1: 基礎知識・準備（車種別） | E1: 部品選定・レビュー | F1: センサ・計測データ | G1: CAN通信・周辺機器連携 | H1: 配線・ピンアサイン資料 | I1: 他社ECU・機器情報 | J1: まとめ・振り返り | K1: 電子工作・自作ツール | L1: その他 | M1: 合計
A2: アルトワークス(HA22S/HA23S) | B2: =COUNTIFS(車種展開_Pivot用!$B$2:$B$320,$A2,車種展開_Pivot用!$C$2:$C$320,B$1) | C2: =COUNTIFS(車種展開_Pivot用!$B$2:$B$320,$A2,車種展開_Pivot用!$C$2:$C$320,C$1) | D2: =COUNTIFS(車種展開_Pivot用!$B$2:$B$320,$A2,車種展開_Pivot用!$C$2:$C$320,D$1) | E2: =COUNTIFS(車種展開_Pivot用!$B$2:$B$320,$A2,車種展開_Pivot用!$C$2:$C$320,E$1) | F2: =COUNTIFS(車種展開_Pivot用!$B$2:$B$320,$A2,車種展開_Pivot用!$C$2:$C$320,F$1) | G2: =COUNTIFS(車種展開_Pivot用!$B$2:$B$320,$A2,車種展開_Pivot用!$C$2:$C$320,G$1) | H2: =COUNTIFS(車種展開_Pivot用!$B$2:$B$320,$A2,車種展開_Pivot用!$C$2:$C$320,H$1) | I2: =COUNTIFS(車種展開_Pivot用!$B$2:$B$320,$A2,車種展開_Pivot用!$C$2:$C$320,I$1) | ... L2: =COUNTIFS(車種展開_Pivot用!$B$2:$B$320,$A2,車種展開_Pivot用!$C$2:$C$320,L$1) | M2: =SUM(B2:L2)
A3: ソニカ(SONICA) | B3: =COUNTIFS(車種展開_Pivot用!$B$2:$B$320,$A3,車種展開_Pivot用!$C$2:$C$320,B$1) | C3: =COUNTIFS(車種展開_Pivot用!$B$2:$B$320,$A3,車種展開_Pivot用!$C$2:$C$320,C$1) | D3: =COUNTIFS(車種展開_Pivot用!$B$2:$B$320,$A3,車種展開_Pivot用!$C$2:$C$320,D$1) | E3: =COUNTIFS(車種展開_Pivot用!$B$2:$B$320,$A3,車種展開_Pivot用!$C$2:$C$320,E$1) | F3: =COUNTIFS(車種展開_Pivot用!$B$2:$B$320,$A3,車種展開_Pivot用!$C$2:$C$320,F$1) | G3: =COUNTIFS(車種展開_Pivot用!$B$2:$B$320,$A3,車種展開_Pivot用!$C$2:$C$320,G$1) | H3: =COUNTIFS(車種展開_Pivot用!$B$2:$B$320,$A3,車種展開_Pivot用!$C$2:$C$320,H$1) | I3: =COUNTIFS(車種展開_Pivot用!$B$2:$B$320,$A3,車種展開_Pivot用!$C$2:$C$320,I$1) | ... L3: =COUNTIFS(車種展開_Pivot用!$B$2:$B$320,$A3,車種展開_Pivot用!$C$2:$C$320,L$1) | M3: =SUM(B3:L3)
A4: エッセ(ESSE) | B4: =COUNTIFS(車種展開_Pivot用!$B$2:$B$320,$A4,車種展開_Pivot用!$C$2:$C$320,B$1) | C4: =COUNTIFS(車種展開_Pivot用!$B$2:$B$320,$A4,車種展開_Pivot用!$C$2:$C$320,C$1) | D4: =COUNTIFS(車種展開_Pivot用!$B$2:$B$320,$A4,車種展開_Pivot用!$C$2:$C$320,D$1) | E4: =COUNTIFS(車種展開_Pivot用!$B$2:$B$320,$A4,車種展開_Pivot用!$C$2:$C$320,E$1) | F4: =COUNTIFS(車種展開_Pivot用!$B$2:$B$320,$A4,車種展開_Pivot用!$C$2:$C$320,F$1) | G4: =COUNTIFS(車種展開_Pivot用!$B$2:$B$320,$A4,車種展開_Pivot用!$C$2:$C$320,G$1) | H4: =COUNTIFS(車種展開_Pivot用!$B$2:$B$320,$A4,車種展開_Pivot用!$C$2:$C$320,H$1) | I4: =COUNTIFS(車種展開_Pivot用!$B$2:$B$320,$A4,車種展開_Pivot用!$C$2:$C$320,I$1) | ... L4: =COUNTIFS(車種展開_Pivot用!$B$2:$B$320,$A4,車種展開_Pivot用!$C$2:$C$320,L$1) | M4: =SUM(B4:L4)
A5: ロードスター(NB8/NB1) | B5: =COUNTIFS(車種展開_Pivot用!$B$2:$B$320,$A5,車種展開_Pivot用!$C$2:$C$320,B$1) | C5: =COUNTIFS(車種展開_Pivot用!$B$2:$B$320,$A5,車種展開_Pivot用!$C$2:$C$320,C$1) | D5: =COUNTIFS(車種展開_Pivot用!$B$2:$B$320,$A5,車種展開_Pivot用!$C$2:$C$320,D$1) | E5: =COUNTIFS(車種展開_Pivot用!$B$2:$B$320,$A5,車種展開_Pivot用!$C$2:$C$320,E$1) | F5: =COUNTIFS(車種展開_Pivot用!$B$2:$B$320,$A5,車種展開_Pivot用!$C$2:$C$320,F$1) | G5: =COUNTIFS(車種展開_Pivot用!$B$2:$B$320,$A5,車種展開_Pivot用!$C$2:$C$320,G$1) | H5: =COUNTIFS(車種展開_Pivot用!$B$2:$B$320,$A5,車種展開_Pivot用!$C$2:$C$320,H$1) | I5: =COUNTIFS(車種展開_Pivot用!$B$2:$B$320,$A5,車種展開_Pivot用!$C$2:$C$320,I$1) | ... L5: =COUNTIFS(車種展開_Pivot用!$B$2:$B$320,$A5,車種展開_Pivot用!$C$2:$C$320,L$1) | M5: =SUM(B5:L5)
A6: FD3S(RX-7) | B6: =COUNTIFS(車種展開_Pivot用!$B$2:$B$320,$A6,車種展開_Pivot用!$C$2:$C$320,B$1) | C6: =COUNTIFS(車種展開_Pivot用!$B$2:$B$320,$A6,車種展開_Pivot用!$C$2:$C$320,C$1) | D6: =COUNTIFS(車種展開_Pivot用!$B$2:$B$320,$A6,車種展開_Pivot用!$C$2:$C$320,D$1) | E6: =COUNTIFS(車種展開_Pivot用!$B$2:$B$320,$A6,車種展開_Pivot用!$C$2:$C$320,E$1) | F6: =COUNTIFS(車種展開_Pivot用!$B$2:$B$320,$A6,車種展開_Pivot用!$C$2:$C$320,F$1) | G6: =COUNTIFS(車種展開_Pivot用!$B$2:$B$320,$A6,車種展開_Pivot用!$C$2:$C$320,G$1) | H6: =COUNTIFS(車種展開_Pivot用!$B$2:$B$320,$A6,車種展開_Pivot用!$C$2:$C$320,H$1) | I6: =COUNTIFS(車種展開_Pivot用!$B$2:$B$320,$A6,車種展開_Pivot用!$C$2:$C$320,I$1) | ... L6: =COUNTIFS(車種展開_Pivot用!$B$2:$B$320,$A6,車種展開_Pivot用!$C$2:$C$320,L$1) | M6: =SUM(B6:L6)
A7: カプチーノ(F6A) | B7: =COUNTIFS(車種展開_Pivot用!$B$2:$B$320,$A7,車種展開_Pivot用!$C$2:$C$320,B$1) | C7: =COUNTIFS(車種展開_Pivot用!$B$2:$B$320,$A7,車種展開_Pivot用!$C$2:$C$320,C$1) | D7: =COUNTIFS(車種展開_Pivot用!$B$2:$B$320,$A7,車種展開_Pivot用!$C$2:$C$320,D$1) | E7: =COUNTIFS(車種展開_Pivot用!$B$2:$B$320,$A7,車種展開_Pivot用!$C$2:$C$320,E$1) | F7: =COUNTIFS(車種展開_Pivot用!$B$2:$B$320,$A7,車種展開_Pivot用!$C$2:$C$320,F$1) | G7: =COUNTIFS(車種展開_Pivot用!$B$2:$B$320,$A7,車種展開_Pivot用!$C$2:$C$320,G$1) | H7: =COUNTIFS(車種展開_Pivot用!$B$2:$B$320,$A7,車種展開_Pivot用!$C$2:$C$320,H$1) | I7: =COUNTIFS(車種展開_Pivot用!$B$2:$B$320,$A7,車種展開_Pivot用!$C$2:$C$320,I$1) | ... L7: =COUNTIFS(車種展開_Pivot用!$B$2:$B$320,$A7,車種展開_Pivot用!$C$2:$C$320,L$1) | M7: =SUM(B7:L7)
A8: Porsche996 | B8: =COUNTIFS(車種展開_Pivot用!$B$2:$B$320,$A8,車種展開_Pivot用!$C$2:$C$320,B$1) | C8: =COUNTIFS(車種展開_Pivot用!$B$2:$B$320,$A8,車種展開_Pivot用!$C$2:$C$320,C$1) | D8: =COUNTIFS(車種展開_Pivot用!$B$2:$B$320,$A8,車種展開_Pivot用!$C$2:$C$320,D$1) | E8: =COUNTIFS(車種展開_Pivot用!$B$2:$B$320,$A8,車種展開_Pivot用!$C$2:$C$320,E$1) | F8: =COUNTIFS(車種展開_Pivot用!$B$2:$B$320,$A8,車種展開_Pivot用!$C$2:$C$320,F$1) | G8: =COUNTIFS(車種展開_Pivot用!$B$2:$B$320,$A8,車種展開_Pivot用!$C$2:$C$320,G$1) | H8: =COUNTIFS(車種展開_Pivot用!$B$2:$B$320,$A8,車種展開_Pivot用!$C$2:$C$320,H$1) | I8: =COUNTIFS(車種展開_Pivot用!$B$2:$B$320,$A8,車種展開_Pivot用!$C$2:$C$320,I$1) | ... L8: =COUNTIFS(車種展開_Pivot用!$B$2:$B$320,$A8,車種展開_Pivot用!$C$2:$C$320,L$1) | M8: =SUM(B8:L8)
A9: AE86 | B9: =COUNTIFS(車種展開_Pivot用!$B$2:$B$320,$A9,車種展開_Pivot用!$C$2:$C$320,B$1) | C9: =COUNTIFS(車種展開_Pivot用!$B$2:$B$320,$A9,車種展開_Pivot用!$C$2:$C$320,C$1) | D9: =COUNTIFS(車種展開_Pivot用!$B$2:$B$320,$A9,車種展開_Pivot用!$C$2:$C$320,D$1) | E9: =COUNTIFS(車種展開_Pivot用!$B$2:$B$320,$A9,車種展開_Pivot用!$C$2:$C$320,E$1) | F9: =COUNTIFS(車種展開_Pivot用!$B$2:$B$320,$A9,車種展開_Pivot用!$C$2:$C$320,F$1) | G9: =COUNTIFS(車種展開_Pivot用!$B$2:$B$320,$A9,車種展開_Pivot用!$C$2:$C$320,G$1) | H9: =COUNTIFS(車種展開_Pivot用!$B$2:$B$320,$A9,車種展開_Pivot用!$C$2:$C$320,H$1) | I9: =COUNTIFS(車種展開_Pivot用!$B$2:$B$320,$A9,車種展開_Pivot用!$C$2:$C$320,I$1) | ... L9: =COUNTIFS(車種展開_Pivot用!$B$2:$B$320,$A9,車種展開_Pivot用!$C$2:$C$320,L$1) | M9: =SUM(B9:L9)
A10: コペン(L880K) | B10: =COUNTIFS(車種展開_Pivot用!$B$2:$B$320,$A10,車種展開_Pivot用!$C$2:$C$320,B$1) | C10: =COUNTIFS(車種展開_Pivot用!$B$2:$B$320,$A10,車種展開_Pivot用!$C$2:$C$320,C$1) | D10: =COUNTIFS(車種展開_Pivot用!$B$2:$B$320,$A10,車種展開_Pivot用!$C$2:$C$320,D$1) | E10: =COUNTIFS(車種展開_Pivot用!$B$2:$B$320,$A10,車種展開_Pivot用!$C$2:$C$320,E$1) | F10: =COUNTIFS(車種展開_Pivot用!$B$2:$B$320,$A10,車種展開_Pivot用!$C$2:$C$320,F$1) | G10: =COUNTIFS(車種展開_Pivot用!$B$2:$B$320,$A10,車種展開_Pivot用!$C$2:$C$320,G$1) | H10: =COUNTIFS(車種展開_Pivot用!$B$2:$B$320,$A10,車種展開_Pivot用!$C$2:$C$320,H$1) | I10: =COUNTIFS(車種展開_Pivot用!$B$2:$B$320,$A10,車種展開_Pivot用!$C$2:$C$320,I$1) | ... L10: =COUNTIFS(車種展開_Pivot用!$B$2:$B$320,$A10,車種展開_Pivot用!$C$2:$C$320,L$1) | M10: =SUM(B10:L10)
A11: ケータハムスーパー7(620R) | B11: =COUNTIFS(車種展開_Pivot用!$B$2:$B$320,$A11,車種展開_Pivot用!$C$2:$C$320,B$1) | C11: =COUNTIFS(車種展開_Pivot用!$B$2:$B$320,$A11,車種展開_Pivot用!$C$2:$C$320,C$1) | D11: =COUNTIFS(車種展開_Pivot用!$B$2:$B$320,$A11,車種展開_Pivot用!$C$2:$C$320,D$1) | E11: =COUNTIFS(車種展開_Pivot用!$B$2:$B$320,$A11,車種展開_Pivot用!$C$2:$C$320,E$1) | F11: =COUNTIFS(車種展開_Pivot用!$B$2:$B$320,$A11,車種展開_Pivot用!$C$2:$C$320,F$1) | G11: =COUNTIFS(車種展開_Pivot用!$B$2:$B$320,$A11,車種展開_Pivot用!$C$2:$C$320,G$1) | H11: =COUNTIFS(車種展開_Pivot用!$B$2:$B$320,$A11,車種展開_Pivot用!$C$2:$C$320,H$1) | I11: =COUNTIFS(車種展開_Pivot用!$B$2:$B$320,$A11,車種展開_Pivot用!$C$2:$C$320,I$1) | ... L11: =COUNTIFS(車種展開_Pivot用!$B$2:$B$320,$A11,車種展開_Pivot用!$C$2:$C$320,L$1) | M11: =SUM(B11:L11)
A12: S2000 | B12: =COUNTIFS(車種展開_Pivot用!$B$2:$B$320,$A12,車種展開_Pivot用!$C$2:$C$320,B$1) | C12: =COUNTIFS(車種展開_Pivot用!$B$2:$B$320,$A12,車種展開_Pivot用!$C$2:$C$320,C$1) | D12: =COUNTIFS(車種展開_Pivot用!$B$2:$B$320,$A12,車種展開_Pivot用!$C$2:$C$320,D$1) | E12: =COUNTIFS(車種展開_Pivot用!$B$2:$B$320,$A12,車種展開_Pivot用!$C$2:$C$320,E$1) | F12: =COUNTIFS(車種展開_Pivot用!$B$2:$B$320,$A12,車種展開_Pivot用!$C$2:$C$320,F$1) | G12: =COUNTIFS(車種展開_Pivot用!$B$2:$B$320,$A12,車種展開_Pivot用!$C$2:$C$320,G$1) | H12: =COUNTIFS(車種展開_Pivot用!$B$2:$B$320,$A12,車種展開_Pivot用!$C$2:$C$320,H$1) | I12: =COUNTIFS(車種展開_Pivot用!$B$2:$B$320,$A12,車種展開_Pivot用!$C$2:$C$320,I$1) | ... L12: =COUNTIFS(車種展開_Pivot用!$B$2:$B$320,$A12,車種展開_Pivot用!$C$2:$C$320,L$1) | M12: =SUM(B12:L12)
A13: NSX | B13: =COUNTIFS(車種展開_Pivot用!$B$2:$B$320,$A13,車種展開_Pivot用!$C$2:$C$320,B$1) | C13: =COUNTIFS(車種展開_Pivot用!$B$2:$B$320,$A13,車種展開_Pivot用!$C$2:$C$320,C$1) | D13: =COUNTIFS(車種展開_Pivot用!$B$2:$B$320,$A13,車種展開_Pivot用!$C$2:$C$320,D$1) | E13: =COUNTIFS(車種展開_Pivot用!$B$2:$B$320,$A13,車種展開_Pivot用!$C$2:$C$320,E$1) | F13: =COUNTIFS(車種展開_Pivot用!$B$2:$B$320,$A13,車種展開_Pivot用!$C$2:$C$320,F$1) | G13: =COUNTIFS(車種展開_Pivot用!$B$2:$B$320,$A13,車種展開_Pivot用!$C$2:$C$320,G$1) | H13: =COUNTIFS(車種展開_Pivot用!$B$2:$B$320,$A13,車種展開_Pivot用!$C$2:$C$320,H$1) | I13: =COUNTIFS(車種展開_Pivot用!$B$2:$B$320,$A13,車種展開_Pivot用!$C$2:$C$320,I$1) | ... L13: =COUNTIFS(車種展開_Pivot用!$B$2:$B$320,$A13,車種展開_Pivot用!$C$2:$C$320,L$1) | M13: =SUM(B13:L13)
A14: （共通・車種特定なし） | B14: =COUNTIFS(車種展開_Pivot用!$B$2:$B$320,$A14,車種展開_Pivot用!$C$2:$C$320,B$1) | C14: =COUNTIFS(車種展開_Pivot用!$B$2:$B$320,$A14,車種展開_Pivot用!$C$2:$C$320,C$1) | D14: =COUNTIFS(車種展開_Pivot用!$B$2:$B$320,$A14,車種展開_Pivot用!$C$2:$C$320,D$1) | E14: =COUNTIFS(車種展開_Pivot用!$B$2:$B$320,$A14,車種展開_Pivot用!$C$2:$C$320,E$1) | F14: =COUNTIFS(車種展開_Pivot用!$B$2:$B$320,$A14,車種展開_Pivot用!$C$2:$C$320,F$1) | G14: =COUNTIFS(車種展開_Pivot用!$B$2:$B$320,$A14,車種展開_Pivot用!$C$2:$C$320,G$1) | H14: =COUNTIFS(車種展開_Pivot用!$B$2:$B$320,$A14,車種展開_Pivot用!$C$2:$C$320,H$1) | I14: =COUNTIFS(車種展開_Pivot用!$B$2:$B$320,$A14,車種展開_Pivot用!$C$2:$C$320,I$1) | ... L14: =COUNTIFS(車種展開_Pivot用!$B$2:$B$320,$A14,車種展開_Pivot用!$C$2:$C$320,L$1) | M14: =SUM(B14:L14)
A15: 合計 | B15: =SUM(B2:B14) | C15: =SUM(C2:C14) | D15: =SUM(D2:D14) | E15: =SUM(E2:E14) | F15: =SUM(F2:F14) | G15: =SUM(G2:G14) | H15: =SUM(H2:H14) | I15: =SUM(I2:I14) | ... M15: =SUM(M2:M14)

Sheet フルコン化ツリー
A1: 階層 | B1: STEP/順序 | C1: タイトル | D1: ECU | E1: 公開日 | F1: 価格 | G1: マガジン名 | H1: note URL
A2: ■ アルトワークス(HA22S/HA23S) | B2: 82件
A3: ◆ STEP本編（フルコン化手順） | B3: 51件
A4: ・ | B4: STEP0 | C4: HA22Sフルコン化 STEP0 ECUピンアサイン | E4: 2025-03-08 | F4: 500 | G4: 新規格 K6A フルコン化情報/アルトワークス フルコン化 HA22S事例 | H4: https://note.com/labratory_ktech/n/na152494670ac
A5: ・ | B5: STEP1 | C5: HA22S K6A フルコン化 STEP1 ビギーバックハーネス | D5: LINKECU | E5: 2025-03-08 | F5: 0 | G5: アルトワークス フルコン化 HA22S事例 | H5: https://note.com/labratory_ktech/n/ne2f733362693
A6: ・ | B6: STEP2 | C6: HA22S LINKECU フルコン化 STEP2 電源供給 | D6: LINKECU | E6: 2025-03-09 | F6: 0 | G6: アルトワークス フルコン化 HA22S事例/ECUフルコン化への道 | H6: https://note.com/labratory_ktech/n/n3bb503e48ff8
A7: ・ | B7: STEP3 | C7: HA22S フルコン化 STEP3 スロットル信号入力とアナログ入力エラー設定の観点 | D7: LINKECU | E7: 2025-03-11 | F7: 100 | G7: アルトワークス フルコン化 HA22S事例/ECUフルコン化への道 | H7: https://note.com/labratory_ktech/n/n58a1cbff1549
A8: ・ | B8: STEP4 | C8: HA22S フルコン化 STEP4 吸気圧力信号入力 と センサCaliblation設定の観点 | D8: LINKECU | E8: 2025-03-16 | F8: 0 | G8: アルトワークス フルコン化 HA22S事例/ECUフルコン化への道 | H8: https://note.com/labratory_ktech/n/nb5f07fceb9fa
A9: ・ | B9: STEP5 | C9: HA22S フルコン化 STEP5 温度センサ校正設定 | D9: LINKECU | E9: 2025-03-29 | F9: 2000 | G9: 新規格 K6A フルコン化情報/アルトワークス フルコン化 HA22S事例/温度センサ関連 | H9: https://note.com/labratory_ktech/n/ne1c5b4e41aba
A10: ・ | B10: STEP5-2 | C10: HA22S K6A フルコン化 STEP5-2 吸気温度センサ 高速度応答化の勧め 吸気温度の“遅れ”がパワーを落としているかも？ | E10: 2025-12-12 | F10: 200 | G10: アルトワークス フルコン化 HA22S事例/LINKECU 関連/パーツレビュー/温度センサ関連/ECUフルコン化への道 | H10: https://note.com/labratory_ktech/n/n204b41865d7b
A11: ・ | B11: STEP5-3 | C11: HA22S LINKECU フルコン化 STEP5-3 スタンドアローン化 温度入力 プルアップON編 | D11: LINKECU | E11: 2025-12-11 | F11: 100 | G11: アルトワークス フルコン化 HA22S事例/LINKECU 関連 | H11: https://note.com/labratory_ktech/n/nbcfdc30b2924
A12: ・ | B12: STEP6 | C12: HA22S フルコン化 STEP6 回転数トリガ設定 | D12: LINKECU | E12: 2025-03-30 | F12: 100 | G12: アルトワークス フルコン化 HA22S事例/ECUフルコン化への道 | H12: https://note.com/labratory_ktech/n/nb50b3a888601
A13: ・ | B13: STEP7 | C13: HA22S フルコン化 STEP7 エンジン設定 | D13: LINKECU | E13: 2025-04-02 | F13: 0 | G13: 新規格 K6A フルコン化情報/アルトワークス フルコン化 HA22S事例 | H13: https://note.com/labratory_ktech/n/n051d663a2b38
A14: ・ | B14: STEP8 | C14: HA22S フルコン化 STEP8 点火テスト | D14: LINKECU | E14: 2025-04-22 | F14: 0 | G14: アルトワークス フルコン化 HA22S事例 | H14: https://note.com/labratory_ktech/n/n2c4e23a28e89
A15: ・ | B15: STEP9 | C15: HA22S フルコン化 STEP9 点火基準合わせ | D15: LINKECU | E15: 2025-05-03 | F15: 500 | G15: アルトワークス フルコン化 HA22S事例/ECUフルコン化への道 | H15: https://note.com/labratory_ktech/n/n0042b76e88d5
A16: ・ | B16: STEP10 | C16: HA22S LINKECU フルコン化 STEP10 車速入力 | D16: LINKECU | E16: 2025-05-21 | F16: 100 | G16: 新規格 K6A フルコン化情報/アルトワークス フルコン化 HA22S事例 | H16: https://note.com/labratory_ktech/n/na48afe8958ff
A17: ・ | B17: STEP10-2 | C17: HA22S LINKECU フルコン スタンドアローン化 STEP10-2 車速信号線スタンドアロン入力 | D17: LINKECU | E17: 2025-12-08 | F17: 100 | G17: アルトワークス フルコン化 HA22S事例 | H17: https://note.com/labratory_ktech/n/n9c7cac38153c
A18: ・ | B18: STEP11 | C18: HA22S LINKECU フルコン化 STEP11 ギヤ認識 | D18: LINKECU | E18: 2025-05-23 | F18: 200 | G18: アルトワークス フルコン化 HA22S事例/ECUフルコン化への道 | H18: https://note.com/labratory_ktech/n/n072b717d733e
A19: ・ | B19: STEP12 | C19: HA22S LINKECU フルコン化 STEP12 デジタルインプット 電気負荷信号入力 | D19: LINKECU | E19: 2025-06-04 | F19: 100 | G19: アルトワークス フルコン化 HA22S事例 | H19: https://note.com/labratory_ktech/n/n7c61e01cdbb0
A20: ・ | B20: STEP13 | C20: HA22S LINKECU フルコン化 STEP13 デジタルインプット ブロアファン信号入力 | D20: LINKECU | E20: 2025-06-07 | F20: 100 | G20: アルトワークス フルコン化 HA22S事例 | H20: https://note.com/labratory_ktech/n/n21ee0a0eae4c
A21: ・ | B21: STEP14 | C21: HA22S LINKECU フルコン化 STEP14 デジタルインプット エアコンリクエスト信号入力 | D21: LINKECU | E21: 2025-06-09 | F21: 100 | G21: アルトワークス フルコン化 HA22S事例 | H21: https://note.com/labratory_ktech/n/n23416a4613b9
A22: ・ | B22: STEP14-2 | C22: HA22S LINKECU フルコン化 STEP14-2 エアコンクラッチOUTPUT 置き換え | D22: LINKECU | E22: 2025-09-27 | F22: 200 | G22: 新規格 K6A フルコン化情報/アルトワークス フルコン化 HA22S事例 | H22: https://note.com/labratory_ktech/n/nee94b9551b76
... A54: ・ | B54: STEP31 | C54: HA22S LINKECU フルコン スタンドアローン化 STEP31 センサ電源５V出力置き換え | D54: LINKECU | E54: 2025-12-08 | F54: 0 | G54: アルトワークス フルコン化 HA22S事例 | H54: https://note.com/labratory_ktech/n/nc7caf9cf0e95
A55: ◆ 基礎知識・準備 | B55: 9件
A56: ・ | B56: 2025-03-10 | C56: 温度センサ校正の基礎知識 分圧とは？ | E56: 2025-03-10 | F56: 0 | G56: アルトワークス フルコン化 HA22S事例/ECUフルコン化への道 | H56: https://note.com/labratory_ktech/n/ne58f6db01abe
A57: ・ | B57: 2025-06-01 | C57: スイッチ入力の基礎 Hisideインプット Losideインプット プルアップ抵抗 プルダウン抵抗 | D57: LINKECU | E57: 2025-06-01 | F57: 500 | G57: アルトワークス フルコン化 HA22S事例/ECUフルコン化への道 | H57: https://note.com/labratory_ktech/n/nc8a5ba6e5875
A58: ・ | B58: 2025-07-17 | C58: LINKECU フルコン化 CEライト設定 LINKがエンジンチェックランプ を点灯する条件は？ | D58: LINKECU | E58: 2025-07-17 | F58: 0 | G58: アルトワークス フルコン化 HA22S事例/LINKECU 関連 | H58: https://note.com/labratory_ktech/n/n33600240af5a
A59: ・ | B59: 2025-07-20 | C59: LINKECU フルコン化 LINKECUの エンジンチェックランプを消すには？ ボタンを付けないでフォルトをクリアする設定方法も紹介！ | D59: LINKECU | E59: 2025-07-20 | F59: 500 | G59: アルトワークス フルコン化 HA22S事例/LINKECU 関連 | H59: https://note.com/labratory_ktech/n/n1aa7874de3ad
A60: ・ | B60: 2025-07-29 | C60: LINKECU フルコン化 ノック Knock 振幅ゲイン調整 | D60: LINKECU | E60: 2025-07-29 | F60: 500 | G60: アルトワークス フルコン化 HA22S事例/LINKECU 関連 | H60: https://note.com/labratory_ktech/n/nad82cb347b90
A61: ・ | B61: 2025-08-09 | C61: LINKECU フルコン化 ノック Knock 気筒毎 Gain調整 気筒補正 | D61: LINKECU | E61: 2025-08-09 | F61: 400 | G61: 新規格 K6A フルコン化情報/アルトワークス フルコン化 HA22S事例/LINKECU 関連 | H61: https://note.com/labratory_ktech/n/nee136e77b006
A62: ・ | B62: 2025-08-16 | C62: LINKECU フルコン化 ノック リタード設定 と Knock igntion Trim MAP | D62: LINKECU | E62: 2025-08-16 | F62: 400 | G62: アルトワークス フルコン化 HA22S事例/LINKECU 関連 | H62: https://note.com/labratory_ktech/n/n22460f8dfcd3
A63: ・ | B63: 2026-02-03 | C63: HA22S LINKECUフルコン化 各STEP | D63: LINKECU | E63: 2026-02-03 | F63: 0 | G63: 新規格 K6A フルコン化情報/アルトワークス フルコン化 HA22S事例/ECUフルコン化への道 | H63: https://note.com/labratory_ktech/n/n6100bb08eea1
A64: ・ | B64: 2026-09-09 | C64: LINKECUで インタークーラー ウォータースプレー ポンプ を制御する HA22S トップマウントＩＣ事例 と ECU設定観点 | D64: LINKECU | E64: 2026-09-09 | F64: 300 | G64: 新規格 K6A フルコン化情報/アルトワークス フルコン化 HA22S事例/LINKECU 関連 | H64: https://note.com/labratory_ktech/n/na74a95906e2e
A65: ◆ 基礎知識・準備（車種別） | B65: 4件
A66: ・ | B66: 2025-03-08 | C66: HA22S K6A アルトワークスフルコン化 | D66: LINKECU | E66: 2025-03-08 | F66: 0 | G66: アルトワークス フルコン化 HA22S事例 | H66: https://note.com/labratory_ktech/n/n3eb953f776fe
A67: ・ | B67: 2025-08-03 | C67: LINKECU フルコン化 ノック Knock LIMIT（閾値）設定 ブースト領域編 | D67: LINKECU/MaxxECU | E67: 2025-08-03 | F67: 300 | G67: アルトワークス フルコン化 HA22S事例 | H67: https://note.com/labratory_ktech/n/ne12a279f64a8
A68: ・ | B68: 2025-08-07 | C68: 新規格K6A LINKECU フルコン化 ビギーバック 点火制御置き換え時のアイドルアップ対策 ラパン KEI等 | D68: LINKECU | E68: 2025-08-07 | F68: 1000 | G68: 新規格 K6A フルコン化情報/アルトワークス フルコン化 HA22S事例 | H68: https://note.com/labratory_ktech/n/n19445cb0e53d
A69: ・ | B69: 2025-12-09 | C69: HA22S LINKECU フルコン スタンドアローン化 アナログ入力 デジタル入力 ビギーバック配線撤去 設定変更なし編 | D69: LINKECU | E69: 2025-12-09 | F69: 0 | G69: アルトワークス フルコン化 HA22S事例 | H69: https://note.com/labratory_ktech/n/nae42f2e73fc3
A70: ◆ 部品選定・レビュー | B70: 11件
A71: ・ | B71: 2025-03-13 | C71: HA22 温度センサー 温度-抵抗特性測定結果 | E71: 2025-03-13 | F71: 500 | G71: アルトワークス フルコン化 HA22S事例/HA22S 部品関連情報/温度センサ関連 | H71: https://note.com/labratory_ktech/n/n6cea0c075bb5
A72: ・ | B72: 2025-08-11 | C72: 失火するコイル？ コイルベンチマーク測定結果紹介 コイル特性の数値はどうだったのか？ | D72: LINKECU | E72: 2025-08-11 | F72: 500 | G72: 新規格 K6A フルコン化情報/HA22S 部品関連情報/パーツレビュー/点火コイル Dwell timeまとめ | H72: https://note.com/labratory_ktech/n/n8248984dd56b
A73: ・ | B73: 2025-12-23 | C73: アナログ ロータリースイッチ制作 ブーストコントロール等スイッチ切り替え 作り方紹介 | E73: 2025-12-23 | F73: 600 | G73: LINKECU 関連/HA22S 部品関連情報/パーツレビュー/ECUフルコン化への道 | H73: https://note.com/labratory_ktech/n/n5f93b4de768b
A74: ・ | B74: 2026-01-01 | C74: HA22S K6Aチューニング ヤフオク容量UP インタークーラー を使ったら吸気温度はどう変わったか？ | E74: 2026-01-01 | F74: 100 | G74: 新規格 K6A フルコン化情報/アルトワークス フルコン化 HA22S事例/HA22S 部品関連情報 | H74: https://note.com/labratory_ktech/n/nfcfcc3bec4b4
A75: ・ | B75: 2026-01-01 | C75: HA22S K6A チューニング アルトにMC21S純正インタークーラーを流用したら、吸気温度はどう変わったか？ | E75: 2026-01-01 | F75: 0 | G75: 新規格 K6A フルコン化情報/アルトワークス フルコン化 HA22S事例/HA22S 部品関連情報 | H75: https://note.com/labratory_ktech/n/n9c8bb1a33274
A76: ・ | B76: 2026-01-03 | C76: HA22S アルトワークス チューニング オイルクーラー取り付け 水温 吸気温度 の 低減効果確認 | E76: 2026-01-03 | F76: 200 | G76: 新規格 K6A フルコン化情報/アルトワークス フルコン化 HA22S事例/HA22S 部品関連情報 | H76: https://note.com/labratory_ktech/n/n224c2c78e036
A77: ・ | B77: 2026-01-03 | C77: HA22S K6A チューニング事例 トップマウント インタークーラー に 間欠制御 ウォッシャースプレーしたら、吸気温度はどう変わったか？ | E77: 2026-01-03 | F77: 0 | G77: アルトワークス フルコン化 HA22S事例/HA22S 部品関連情報/パーツレビュー | H77: https://note.com/labratory_ktech/n/nc9b534bd13c9
A78: ・ | B78: 2026-01-03 | C78: 吸気温度低減 チューニング インタークーラー ウォータスプレー 準備 スイッチ動作設定 ICWS | E78: 2026-01-03 | F78: 200 | G78: アルトワークス フルコン化 HA22S事例/HA22S 部品関連情報/パーツレビュー | H78: https://note.com/labratory_ktech/n/n73ef3e1654e5
A79: ・ | B79: 2026-03-20 | C79: HA22S K6A チューニング 排気温度計 センサ取付例 EGT Sensor | E79: 2026-03-20 | F79: 0 | G79: 新規格 K6A フルコン化情報/アルトワークス フルコン化 HA22S事例/HA22S 部品関連情報/温度センサ関連 | H79: https://note.com/labratory_ktech/n/n9f112d7ffc9c
A80: ・ | B80: 2026-08-24 | C80: HA22S K6A の 純正燃料ポンプ流量を実測してみた ブーストアップ 時の限界馬力を数値で把握する | D80: LINKECU | E80: 2026-08-24 | F80: 200 | G80: 新規格 K6A フルコン化情報/アルトワークス フルコン化 HA22S事例/パーツレビュー/燃料、インジェクター関連 無効噴射時間 | H80: https://note.com/labratory_ktech/n/nbc29dfe70d48
A81: ・ | B81: 2026-08-29 | C81: HA23 K6A の 純正燃料ポンプ流量を実測してみた 純正ポンプ だとこのくらいの馬力で燃料が足りなくります | E81: 2026-08-29 | F81: 200 | G81: 新規格 K6A フルコン化情報/アルトワークス フルコン化 HA22S事例/HA22S 部品関連情報 | H81: https://note.com/labratory_ktech/n/n80945059ffdc
A82: ◆ センサ・計測データ | B82: 3件
A83: ・ | B83: 2025-03-15 | C83: HA22S 吸気圧力センサ HITACHI製 品番 18590-78G50 特性測定結果 | D83: LINKECU | E83: 2025-03-15 | F83: 2000 | G83: アルトワークス フルコン化 HA22S事例/吸気圧力センサ 電圧-圧力特性測定結果 | H83: https://note.com/labratory_ktech/n/n6cfee691bebe
A84: ・ | B84: 2025-08-14 | C84: ノックセンサ 共振TYPE 非共振TYPEってなんやねん！？ | E84: 2025-08-14 | F84: 300 | G84: アルトワークス フルコン化 HA22S事例/LINKECU 関連/計測器情報/ECUフルコン化への道 | H84: https://note.com/labratory_ktech/n/n6b8f70062b2e
A85: ・ | B85: 2025-09-07 | C85: インジェクター 無効噴射時間 SARD製 380cc/min 青 63567 実測結果 Injector dead Time Short time pulse adder | E85: 2025-09-07 | F85: 20000 | G85: 新規格 K6A フルコン化情報/アルトワークス フルコン化 HA22S事例/燃料、インジェクター関連 無効噴射時間 | H85: https://note.com/labratory_ktech/n/naa6e35e51d37
A86: ◆ CAN通信・周辺機器連携 | B86: 1件
A87: ・ | B87: 2026-01-28 | C87: 測っているEGT、本当に排気温度を見ていますか？ タービン前後の排気温度を同時測定した結果 | D87: ECUMaster(PMU/ADU/EMU) | E87: 2026-01-28 | F87: 500 | G87: アルトワークス フルコン化 HA22S事例/CAN 設定への道/パーツレビュー/温度センサ関連 | H87: https://note.com/labratory_ktech/n/n3abcbbd67bea
A88: ◆ 他社ECU・機器情報 | B88: 1件
A89: ・ | B89: 2026-01-26 | C89: MaxxECU K6A フルコン化 可否確認 ついでにマイコンでTrigger Signal生成してみたよ！ | D89: MaxxECU | E89: 2026-01-26 | F89: 0 | G89: 新規格 K6A フルコン化情報/アルトワークス フルコン化 HA22S事例/MaxxECU フルコン化への道 | H89: https://note.com/labratory_ktech/n/nb6e334dfda5f
A90: ◆ まとめ・振り返り | B90: 1件
A91: ・ | B91: 2025-12-11 | C91: HA22S LINKECU フルコン化 スタンドアローン化 純正ECU取り外し 初級編終了のお知らせ！ | D91: LINKECU | E91: 2025-12-11 | F91: 0 | G91: アルトワークス フルコン化 HA22S事例 | H91: https://note.com/labratory_ktech/n/n5b83d987137a
A92: ◆ その他 | B92: 1件
A93: ・ | B93: 2025-03-16 | C93: HA23 吸気圧力センサ Denso製 品番 18590-79F00 特性測定結果 | D93: LINKECU | E93: 2025-03-16 | F93: 2000 | G93: （未分類） | H93: https://note.com/labratory_ktech/n/n0c63cbb980ee
A94: ■ ソニカ(SONICA) | B94: 55件
A95: ◆ STEP本編（フルコン化手順） | B95: 38件
A96: ・ | B96: STEP1 | C96: KF-DET ソニカ フルコン化への道 STEP1 ビギーバックハーネス購入と不要配線間引き | D96: LINKECU | E96: 2025-10-30 | F96: 0 | G96: ソニカ KF-DET フルコン化 | H96: https://note.com/labratory_ktech/n/n23757810e565
A97: ・ | B97: STEP2 | C97: KF-DET ソニカ フルコン化への道 STEP2 ビギーバック 配線分岐分岐方法と電源ON | E97: 2025-11-02 | F97: 0 | G97: ソニカ KF-DET フルコン化 | H97: https://note.com/labratory_ktech/n/n264936a20aed
A98: ・ | B98: STEP3 | C98: KF-DET ソニカ フルコン化への道 STEP3 TPS信号入力 | E98: 2025-11-02 | F98: 0 | G98: ソニカ KF-DET フルコン化 | H98: https://note.com/labratory_ktech/n/ndb8d9fe9df55
A99: ・ | B99: STEP3-1 | C99: ソニカ KF-DET LINKECU化 STEP3-1 4-2 TPS MAP 配線撤去（スタンドアローン化）したら、ATギヤが切り替わらなくなった(´;ω;｀) 追加調査どっちが必須か調べてみた！ | D99: LINKECU | E99: 2026-07-13 | F99: 0 | G99: ソニカ KF-DET フルコン化 | H99: https://note.com/labratory_ktech/n/n48d75cdf0926
A100: ・ | B100: STEP4 | C100: KF-DET ソニカ LINKECU フルコン化への道 STEP4 吸気圧力センサ信号入力 純正ブースト圧調べてみた！ | D100: LINKECU | E100: 2025-11-02 | F100: 0 | G100: ソニカ KF-DET フルコン化 | H100: https://note.com/labratory_ktech/n/nad0b59073271
A101: ・ | B101: STEP5 | C101: KF-DET ソニカ LINKECU フルコン化への道 STEP5 温度センサ信号入力 電動ファン 動作温度調査 | D101: LINKECU | E101: 2025-11-03 | F101: 300 | G101: ソニカ KF-DET フルコン化/温度センサ関連 | H101: https://note.com/labratory_ktech/n/n508202fdcd2f
A102: ・ | B102: STEP5-1-2 | C102: KF-DET ソニカ LINKECU フルコン化 への道 STEP5-1-2 吸気温度センサ（IAT）信号入力 校正 | D102: LINKECU | E102: 2026-07-21 | F102: 200 | G102: ソニカ KF-DET フルコン化 | H102: https://note.com/labratory_ktech/n/nb2fa775ea433
A103: ・ | B103: STEP6 | C103: KF-DET ソニカ LINKECU フルコン化への道 STEP6 回転数トリガ設定 | D103: LINKECU | E103: 2025-11-04 | F103: 300 | G103: ソニカ KF-DET フルコン化 | H103: https://note.com/labratory_ktech/n/nee4c897d9960
A104: ・ | B104: STEP7 | C104: エッセ KF-VE LINKECU フルコン化 STEP7 エンジン設定 点火 燃料 | D104: LINKECU | E104: 2026-09-01 | F104: 100 | G104: ソニカ KF-DET フルコン化/エッセ ESSE LINKECU フルコン化 への道 | H104: https://note.com/labratory_ktech/n/n536763ecda5a
A105: ・ | B105: STEP8 | C105: ソニカ KF-DET LINKECU フルコン化 STEP8 点火テスト、STEP9 点火基準合わせ | D105: LINKECU | E105: 2025-11-24 | F105: 500 | G105: LINKECU 関連/ソニカ KF-DET フルコン化/エッセ ESSE LINKECU フルコン化 への道 | H105: https://note.com/labratory_ktech/n/nf4cf6f3d6d50
A106: ・ | B106: STEP10 | C106: ソニカ KF-DET LINKECU フルコン化 STEP10 CAN 信号から 車速入力 | D106: LINKECU | E106: 2026-02-08 | F106: 1000 | G106: ソニカ KF-DET フルコン化/CAN 設定への道 | H106: https://note.com/labratory_ktech/n/naa8d10e4bb6f
A107: ・ | B107: STEP13 | C107: ソニカ KF-DET LINKECU化 Step13 ブロアファン 信号入力 車両CAN解析 | D107: LINKECU | E107: 2026-05-01 | F107: 1000 | G107: ソニカ KF-DET フルコン化/CAN 設定への道 | H107: https://note.com/labratory_ktech/n/ne4c45d69fb5b
A108: ・ | B108: STEP14 | C108: ソニカ KF-DET LINKECU化 Step14 A/Cリクエストインプット 車両CAN解析 | D108: LINKECU | E108: 2026-04-30 | F108: 1000 | G108: ソニカ KF-DET フルコン化/CAN 設定への道 | H108: https://note.com/labratory_ktech/n/ndda9a1133681
A109: ・ | B109: STEP14-2 | C109: エッセ KF-VE ソニカ KF-DET LINKECU フルコン化 STEP14-2 エアコンクラッチOUTPUT 置き換え | D109: LINKECU | E109: 2026-05-04 | F109: 100 | G109: ソニカ KF-DET フルコン化/エッセ ESSE LINKECU フルコン化 への道 | H109: https://note.com/labratory_ktech/n/n58b0a206e2ae
A110: ・ | B110: STEP14-3 | C110: エッセ KF-VE ソニカ KF-DET LINKECU フルコン化 STEP14-3 エアコン制御 エバポレーター温度入力 ビギーバック無 スタンドアローン入力編 | D110: LINKECU | E110: 2025-10-12 | F110: 200 | G110: ソニカ KF-DET フルコン化/エッセ ESSE LINKECU フルコン化 への道 | H110: https://note.com/labratory_ktech/n/n38e7e13c5652
... A133: ・ | B133: STEP35 | C133: エッセ KF-VE ソニカ KF-DET LINKECU フルコン化 STEP35 AUX OUT パージソレノイド制御 PURGE | D133: LINKECU | E133: 2026-06-28 | F133: 100 | G133: ソニカ KF-DET フルコン化/エッセ ESSE LINKECU フルコン化 への道 | H133: https://note.com/labratory_ktech/n/n99f766b123d0
A134: ◆ 基礎知識・準備（車種別） | B134: 1件
A135: ・ | B135: 2026-01-13 | C135: エッセにお勧めのフルコンは？ LINECU? MaxxECU? EMTRON? | D135: MaxxECU/EMTRON | E135: 2026-01-13 | F135: 500 | G135: ソニカ KF-DET フルコン化/エッセ ESSE LINKECU フルコン化 への道/エッセ ESSE MaaxxECUフルコン化への道 | H135: https://note.com/labratory_ktech/n/n4b07ef260646
A136: ◆ 部品選定・レビュー | B136: 6件
A137: ・ | B137: 2025-12-28 | C137: ソニカ KF-DET インジェクター流量調査 と 限界馬力予測 同じKF-DETでも違うインジェクター使ってるの！？ | E137: 2025-12-28 | F137: 0 | G137: ソニカ KF-DET フルコン化/パーツレビュー/燃料、インジェクター関連 無効噴射時間 | H137: https://note.com/labratory_ktech/n/n2d9bbc2705aa
A138: ・ | B138: 2026-03-21 | C138: ソニカ KF-DET ブーストUP セッティング開始 と 思ったら ブースト 上がらない(´・ω・｀) 原因は・・・・・そこでしたか・・・・ | E138: 2026-03-21 | F138: 0 | G138: ソニカ KF-DET フルコン化/ソニカ 作業記録 部品メモ/点検整備記録 | H138: https://note.com/labratory_ktech/n/nbbfe1847dfb6
A139: ・ | B139: 2026-03-22 | C139: ソニカ 軽量化 フォグランプ 取り外しの注意観点 | E139: 2026-03-22 | F139: 0 | G139: ソニカ 作業記録 部品メモ | H139: https://note.com/labratory_ktech/n/n4f3956d28200
A140: ・ | B140: 2026-04-23 | C140: ソニカ KF-DET インタークーラー 交換 | E140: 2026-04-23 | F140: 0 | G140: ソニカ 作業記録 部品メモ/点検整備記録 | H140: https://note.com/labratory_ktech/n/n25d647598c04
A141: ・ | B141: 2026-05-28 | C141: ソニカ KF-DET ブースト が 上がらない問題 原因はそこでしたか パート② | E141: 2026-05-28 | F141: 0 | G141: ソニカ KF-DET フルコン化/ソニカ 作業記録 部品メモ/点検整備記録 | H141: https://note.com/labratory_ktech/n/n62113a1e5685
A142: ・ | B142: 2026-06-01 | C142: ソニカ KF-DET ブースト上らない 不具合対策 PCVバルブホース交換 トラブル対策 部品交換 | E142: 2026-06-01 | F142: 0 | G142: ソニカ 作業記録 部品メモ/点検整備記録 | H142: https://note.com/labratory_ktech/n/na159deeaefed
A143: ◆ センサ・計測データ | B143: 4件
A144: ・ | B144: 2025-11-02 | C144: ダイハツ KF-DET 吸気圧力センサ特性 品番 89421-82020 0 261 230 152 MAP sensor | E144: 2025-11-02 | F144: 2000 | G144: ソニカ KF-DET フルコン化/吸気圧力センサ 電圧-圧力特性測定結果 | H144: https://note.com/labratory_ktech/n/n814aa7041178
A145: ・ | B145: 2025-12-21 | C145: エッセ ESSE KF-VE 温度センサー 温度-抵抗特性 と 純正ECU温度プルアップ抵抗確認結果 | D145: 純正ECU | E145: 2025-12-21 | F145: 1500 | G145: ソニカ KF-DET フルコン化/エッセ ESSE LINKECU フルコン化 への道/温度センサ関連 | H145: https://note.com/labratory_ktech/n/nd51711a9b2dc
A146: ・ | B146: 2025-12-29 | C146: ダイハツ ソニカ KF-DET BOSCH インジェクター 無効噴射時間 short time pulse adder 実測結果 Injector dead Time 特性測定結果 | E146: 2025-12-29 | F146: 10000 | G146: ソニカ KF-DET フルコン化/エッセ ESSE LINKECU フルコン化 への道/燃料、インジェクター関連 無効噴射時間 | H146: https://note.com/labratory_ktech/n/n3a1d516a858c
A147: ・ | B147: 2026-05-07 | C147: ソニカ KF-DET プルアップ抵抗 実測結果 水温 吸気温度 エバポレイター温度 | E147: 2026-05-07 | F147: 300 | G147: ソニカ KF-DET フルコン化/温度センサ関連 | H147: https://note.com/labratory_ktech/n/n42bd9311ab8a
A148: ◆ CAN通信・周辺機器連携 | B148: 4件
A149: ・ | B149: 2025-12-16 | C149: ソニカ KF-DET LINKECU フルコン化 車両側 CAN信号 確認編 | D149: LINKECU | E149: 2025-12-16 | F149: 300 | G149: ソニカ KF-DET フルコン化/CAN 設定への道/ECUmaster PMU ADU関連 | H149: https://note.com/labratory_ktech/n/n1abc96102085
A150: ・ | B150: 2026-05-23 | C150: ソニカ KF-DET LINKECU フルコン化 ISCV アイドルUP設定 のための ATギヤポジション CAN入力 CANbus CAN解析 | D150: LINKECU | E150: 2026-05-23 | F150: 500 | G150: ソニカ KF-DET フルコン化/CAN 設定への道 | H150: https://note.com/labratory_ktech/n/n8fbaf7c1c6f2
A151: ・ | B151: 2026-07-04 | C151: ソニカ KF-DET 純正ECUの TPS CAN 信号を調べてみた | D151: 純正ECU | E151: 2026-07-04 | F151: 0 | G151: ソニカ KF-DET フルコン化/CAN 設定への道 | H151: https://note.com/labratory_ktech/n/nf52bb5672260
A152: ・ | B152: 2026-08-27 | C152: ソニカ KF-DET 純正ECUの 回転数 CAN 信号を調べてみた LINKECU で読みに行く設定方法 | D152: LINKECU | E152: 2026-08-27 | F152: 200 | G152: ソニカ KF-DET フルコン化/CAN 設定への道 | H152: https://note.com/labratory_ktech/n/n0a271586e487
A153: ◆ 配線・ピンアサイン資料 | B153: 1件
...
